Workbook
Name insightCritical: '03_Calculations'!$I$25
Name insightDriver: '03_Calculations'!$I$26
Name insightOpportunity: '03_Calculations'!$I$28
Name insightWarning: '03_Calculations'!$I$27
Name kpiChurned: '03_Calculations'!$C$6
Name kpiChurnRate: '03_Calculations'!$C$8
Name kpiExisting: '03_Calculations'!$C$5
Name kpiMRVL: '03_Calculations'!$C$10
Name kpiRetained: '03_Calculations'!$C$7
Name kpiRetentionRate: '03_Calculations'!$C$9
Name nativePivotsReady: '03_Calculations'!$H$2

Sheet 01_Dashboard
A1: CUSTOMER RETENTION INTELLIGENCE | Q1: Q2 2022 • CALIFORNIA
A3: Executive churn health • concentration • drivers • retention opportunity | Q3: 7,043 customers | 454 joined | rates exclude Joined
A4: CONTRACT | I4: TENURE BAND | Q4: INTERNET TYPE
A5: Month-to-Month • One Year • Two Year Native slicer is created here by setup_dashboard.bas | I5: 0–6 months → 49–72 months Native slicer is created here by setup_dashboard.bas | Q5: Fiber Optic • Cable • DSL • (blank = no internet) Native slicer is created here by setup_dashboard.bas
A8: EXISTING CUSTOMERS | E8: CHURNED CUSTOMERS | I8: RETAINED CUSTOMERS | M8: CHURN RATE | Q8: RETENTION RATE | U8: MRVL
A9: =kpiExisting -> 6589 | E9: =kpiChurned -> 1869 | I9: =kpiRetained -> 4720 | M9: =kpiChurnRate -> 0.28365458 | Q9: =kpiRetentionRate -> 0.71634542 | U9: =kpiMRVL -> 137086.65
A11: Active base | E11: Exited | I11: Stayed | M11: Churned ÷ Existing | Q11: Retained ÷ Existing | U11: Monthly value lost
A13: MAIN ANALYSIS | Concentration • associated characteristics • stated reasons • retention priority
A14: CONTRACT × TENURE CHURN CONCENTRATION | Q14: CHURN RATE BY INTERNET TYPE
E15: Month-to-Month | I15: One Year | M15: Two Year | Q15: Which internet technology is associated with elevated churn?
A16: 0-6 months | E16: =IF(nativePivotsReady,IFERROR(GETPIVOTDATA("Churn Rate",'02_Pivots'!$A$52,"Tenure_Band","0-6 months","Contract","Month-to-Month"),""),0.8133472367049009) -> 0.81334724 | I16: =IF(nativePivotsReady,IFERROR(GETPIVOTDATA("Churn Rate",'02_Pivots'!$A$52,"Tenure_Band","0-6 months","Contract","One Year"),""),0.14285714285714285) -> 0.14285714 | M16: =IF(nativePivotsReady,IFERROR(GETPIVOTDATA("Churn Rate",'02_Pivots'!$A$52,"Tenure_Band","0-6 months","Contract","Two Year"),""),0.0) -> 0 | Q16: BASELINE PREVIEW • NATIVE INTERACTIVITY ADDED BY VBA
E17: =IF(nativePivotsReady,IFERROR(GETPIVOTDATA("Existing Customers",'02_Pivots'!$A$52,"Tenure_Band","0-6 months","Contract","Month-to-Month"),""),959) -> 959 | I17: =IF(nativePivotsReady,IFERROR(GETPIVOTDATA("Existing Customers",'02_Pivots'!$A$52,"Tenure_Band","0-6 months","Contract","One Year"),""),28) -> 28 | M17: =IF(nativePivotsReady,IFERROR(GETPIVOTDATA("Existing Customers",'02_Pivots'!$A$52,"Tenure_Band","0-6 months","Contract","Two Year"),""),29) -> 29
A18: 7-12 months | E18: =IF(nativePivotsReady,IFERROR(GETPIVOTDATA("Churn Rate",'02_Pivots'!$A$52,"Tenure_Band","7-12 months","Contract","Month-to-Month"),""),0.4468864468864469) -> 0.44688645 | I18: =IF(nativePivotsReady,IFERROR(GETPIVOTDATA("Churn Rate",'02_Pivots'!$A$52,"Tenure_Band","7-12 months","Contract","One Year"),""),0.09574468085106383) -> 0.095744681 | M18: =IF(nativePivotsReady,IFERROR(GETPIVOTDATA("Churn Rate",'02_Pivots'!$A$52,"Tenure_Band","7-12 months","Contract","Two Year"),""),0.0) -> 0 | Q18: Fiber Optic | W18: 0.42126789
E19: =IF(nativePivotsReady,IFERROR(GETPIVOTDATA("Existing Customers",'02_Pivots'!$A$52,"Tenure_Band","7-12 months","Contract","Month-to-Month"),""),546) -> 546 | I19: =IF(nativePivotsReady,IFERROR(GETPIVOTDATA("Existing Customers",'02_Pivots'!$A$52,"Tenure_Band","7-12 months","Contract","One Year"),""),94) -> 94 | M19: =IF(nativePivotsReady,IFERROR(GETPIVOTDATA("Existing Customers",'02_Pivots'!$A$52,"Tenure_Band","7-12 months","Contract","Two Year"),""),76) -> 76
A20: 13-24 months | E20: =IF(nativePivotsReady,IFERROR(GETPIVOTDATA("Churn Rate",'02_Pivots'!$A$52,"Tenure_Band","13-24 months","Contract","Month-to-Month"),""),0.40524781341107874) -> 0.40524781 | I20: =IF(nativePivotsReady,IFERROR(GETPIVOTDATA("Churn Rate",'02_Pivots'!$A$52,"Tenure_Band","13-24 months","Contract","One Year"),""),0.07441860465116279) -> 0.074418605 | M20: =IF(nativePivotsReady,IFERROR(GETPIVOTDATA("Churn Rate",'02_Pivots'!$A$52,"Tenure_Band","13-24 months","Contract","Two Year"),""),0.0) -> 0
E21: =IF(nativePivotsReady,IFERROR(GETPIVOTDATA("Existing Customers",'02_Pivots'!$A$52,"Tenure_Band","13-24 months","Contract","Month-to-Month"),""),686) -> 686 | I21: =IF(nativePivotsReady,IFERROR(GETPIVOTDATA("Existing Customers",'02_Pivots'!$A$52,"Tenure_Band","13-24 months","Contract","One Year"),""),215) -> 215 | M21: =IF(nativePivotsReady,IFERROR(GETPIVOTDATA("Existing Customers",'02_Pivots'!$A$52,"Tenure_Band","13-24 months","Contract","Two Year"),""),123) -> 123 | Q21: Cable | W21: 0.2751938
A22: 25-36 months | E22: =IF(nativePivotsReady,IFERROR(GETPIVOTDATA("Churn Rate",'02_Pivots'!$A$52,"Tenure_Band","25-36 months","Contract","Month-to-Month"),""),0.3648960739030023) -> 0.36489607 | I22: =IF(nativePivotsReady,IFERROR(GETPIVOTDATA("Churn Rate",'02_Pivots'!$A$52,"Tenure_Band","25-36 months","Contract","One Year"),""),0.07462686567164178) -> 0.074626866 | M22: =IF(nativePivotsReady,IFERROR(GETPIVOTDATA("Churn Rate",'02_Pivots'!$A$52,"Tenure_Band","25-36 months","Contract","Two Year"),""),0.015267175572519083) -> 0.015267176
E23: =IF(nativePivotsReady,IFERROR(GETPIVOTDATA("Existing Customers",'02_Pivots'!$A$52,"Tenure_Band","25-36 months","Contract","Month-to-Month"),""),433) -> 433 | I23: =IF(nativePivotsReady,IFERROR(GETPIVOTDATA("Existing Customers",'02_Pivots'!$A$52,"Tenure_Band","25-36 months","Contract","One Year"),""),268) -> 268 | M23: =IF(nativePivotsReady,IFERROR(GETPIVOTDATA("Existing Customers",'02_Pivots'!$A$52,"Tenure_Band","25-36 months","Contract","Two Year"),""),131) -> 131
A24: 37-48 months | E24: =IF(nativePivotsReady,IFERROR(GETPIVOTDATA("Churn Rate",'02_Pivots'!$A$52,"Tenure_Band","37-48 months","Contract","Month-to-Month"),""),0.375886524822695) -> 0.37588652 | I24: =IF(nativePivotsReady,IFERROR(GETPIVOTDATA("Churn Rate",'02_Pivots'!$A$52,"Tenure_Band","37-48 months","Contract","One Year"),""),0.12589928057553956) -> 0.12589928 | M24: =IF(nativePivotsReady,IFERROR(GETPIVOTDATA("Churn Rate",'02_Pivots'!$A$52,"Tenure_Band","37-48 months","Contract","Two Year"),""),0.019801980198019802) -> 0.01980198 | Q24: DSL | W24: 0.19973975
E25: =IF(nativePivotsReady,IFERROR(GETPIVOTDATA("Existing Customers",'02_Pivots'!$A$52,"Tenure_Band","37-48 months","Contract","Month-to-Month"),""),282) -> 282 | I25: =IF(nativePivotsReady,IFERROR(GETPIVOTDATA("Existing Customers",'02_Pivots'!$A$52,"Tenure_Band","37-48 months","Contract","One Year"),""),278) -> 278 | M25: =IF(nativePivotsReady,IFERROR(GETPIVOTDATA("Existing Customers",'02_Pivots'!$A$52,"Tenure_Band","37-48 months","Contract","Two Year"),""),202) -> 202
A26: 49-72 months | E26: =IF(nativePivotsReady,IFERROR(GETPIVOTDATA("Churn Rate",'02_Pivots'!$A$52,"Tenure_Band","49-72 months","Contract","Month-to-Month"),""),0.30067567567567566) -> 0.30067568 | I26: =IF(nativePivotsReady,IFERROR(GETPIVOTDATA("Churn Rate",'02_Pivots'!$A$52,"Tenure_Band","49-72 months","Contract","One Year"),""),0.12752721617418353) -> 0.12752722 | M26: =IF(nativePivotsReady,IFERROR(GETPIVOTDATA("Churn Rate",'02_Pivots'!$A$52,"Tenure_Band","49-72 months","Contract","Two Year"),""),0.03230769230769231) -> 0.032307692
E27: =IF(nativePivotsReady,IFERROR(GETPIVOTDATA("Existing Customers",'02_Pivots'!$A$52,"Tenure_Band","49-72 months","Contract","Month-to-Month"),""),296) -> 296 | I27: =IF(nativePivotsReady,IFERROR(GETPIVOTDATA("Existing Customers",'02_Pivots'!$A$52,"Tenure_Band","49-72 months","Contract","One Year"),""),643) -> 643 | M27: =IF(nativePivotsReady,IFERROR(GETPIVOTDATA("Existing Customers",'02_Pivots'!$A$52,"Tenure_Band","49-72 months","Contract","Two Year"),""),1300) -> 1300 | Q27: Internet customers only • association, not causation
A29: TOP 5 STATED CHURN REASONS | N29: DESCRIPTIVE CHURN RISK TIERS
A30: What churned customers most often said when leaving | N30: Where elevated churn and meaningful customer volume overlap
A31: BASELINE PREVIEW • NATIVE INTERACTIVITY ADDED BY VBA | N31: BASELINE PREVIEW • NATIVE INTERACTIVITY ADDED BY VBA
A32: Competitor had better devices | M32: 313 | N32: Very High | U32: 0.66512059 | V32: =IF(nativePivotsReady,IFERROR(GETPIVOTDATA("Existing Customers",'02_Pivots'!$F$38,"Descriptive_Churn_Risk_Tier","Very High"),0),2156) -> 2156
A33: Competitor made better offer | M33: 311 | N33: High | U33: 0.20651311 | V33: =IF(nativePivotsReady,IFERROR(GETPIVOTDATA("Existing Customers",'02_Pivots'!$F$38,"Descriptive_Churn_Risk_Tier","High"),0),1259) -> 1259
A34: Attitude of support person | M34: 220 | N34: Medium | U34: 0.072928821 | V34: =IF(nativePivotsReady,IFERROR(GETPIVOTDATA("Existing Customers",'02_Pivots'!$F$38,"Descriptive_Churn_Risk_Tier","Medium"),0),1714) -> 1714
A35: Don't know | M35: 130 | N35: Low | U35: 0.034246575 | V35: =IF(nativePivotsReady,IFERROR(GETPIVOTDATA("Existing Customers",'02_Pivots'!$F$38,"Descriptive_Churn_Risk_Tier","Low"),0),1460) -> 1460
A36: Competitor offered more data | M36: 117
A38: Self-reported exit reasons • not verified causes | N38: Rule-based descriptive tiers • not predictive probabilities
A40: EXECUTIVE INSIGHTS
A41: CRITICAL FINDING | G41: MAJOR DRIVER | M41: EARLY WARNING | S41: BUSINESS OPPORTUNITY
A42: =insightCritical -> Month-to-Month customers have a 51.7% churn rate, the highest contract-level exposure. | G42: =insightDriver -> Churn reaches 77.2% among customers in their first 0–6 months. | M42: =insightWarning -> Month-to-Month + 0–6 months + Fiber records 91.2% churn: 444 of 487 existing customers. | S42: =insightOpportunity -> Fiber churn is 42.1%; better devices (313) and better offers (311) lead stated exit reasons.
A43: Baseline executive context • insight cells are named for future dynamic narratives • associations and stated reasons do not establish causation
A45: BUSINESS RECOMMENDATIONS
A46: 01 EARLY-TENURE SAVE JOURNEY | I46: 02 COMMITMENT MIGRATION | Q46: 03 COMPETITOR VALUE RESPONSE
A48: Rationale | 0–6 month churn is 77.2%; the M2M + 0–6 + Fiber intersection reaches 91.2%. | I48: Rationale | Month-to-Month churn is 51.7%, the strongest contract-level exposure. | Q48: Rationale | Better devices (313) and better offers (311) lead stated reasons; Fiber churn is 42.1%.
A50: Action | Test onboarding check-ins, service recovery and targeted save treatment during the first 90 days. | I50: Action | Test transparent one- and two-year migration offers with clear customer value and safeguards. | Q50: Action | Review the device proposition and test competitive offers for relevant Fiber segments.
A53: EXPECTED IMPACT POTENTIAL • HIGH | I53: EXPECTED IMPACT POTENTIAL • HIGH | Q53: EXPECTED IMPACT POTENTIAL • MEDIUM–HIGH
A55: METHODOLOGY
A56: Churn Rate = Churned ÷ (Churned + Stayed). Joined customers remain in the source but are excluded from churn and retention denominators. Risk tiers are rule-based descriptive segments, not predictive probabilities. Recommendation impact indicators are directional prioritization signals, not forecasts. | S56: Source data/processed/customers_clean.csv Q2 2022 snapshot

Sheet 02_Pivots
A1: Native Pivot Support
A2: Create all six pivots by copying PT_KPI_Context so every slicer can share one PivotCache.
J4: PivotTable | K4: Destination | L4: Rows | M4: Columns | N4: Values | O4: Filters | P4: Dashboard object
J5: PT_KPI_Context | K5: A3 | L5: — | M5: — | N5: Sum Existing, Churned, Retained, MRVL | O5: — | P5: Six KPI cards
J6: PT_InternetType | K6: A12 | L6: Internet Type | M6: — | N6: Average Churn_Rate_Value | O6: Internet Service = Yes | P6: PC_InternetType
J7: PT_ChurnReasons | K7: A24 | L7: Churn Reason | M7: — | N7: Count Customer ID | O7: Status = Churned; Top 5 | P7: PC_ChurnReasons
J8: PT_RiskTier | K8: A38 | L8: Risk Tier | M8: — | N8: Average Churn_Rate_Value | O8: — | P8: PC_RiskTier
J9: PT_RiskTierVolume | K9: F38 | L9: Risk Tier | M9: — | N9: Sum Existing_Flag | O9: — | P9: Risk volume labels
J10: PT_ContractTenure | K10: A52 | L10: Tenure_Band | M10: Contract | N10: Average Churn Rate; Sum Existing | O10: — | P10: Heatmap
J13: Native Excel boundary
J14: Python intentionally does not create PivotTable, PivotChart, slicer, or report-connection XML. Use the exact Phase B runbook in EXCEL_DASHBOARD_BUILD_PLAN.md. Do not resave this workbook with openpyxl or XlsxWriter after native objects are added.

Sheet 03_Calculations
B1: Calculation & Validation Layer | H1: Native pivots ready?
B2: Current values become slicer-responsive when PT_KPI_Context is created in Excel Desktop. | H2: =NOT(ISERROR(GETPIVOTDATA("Existing Customers",'02_Pivots'!$A$3))) -> FALSE
B4: KPI | C4: Current | D4: Baseline | E4: Variance | F4: Status | H4: Helper-field audit
B5: Existing Customers | C5: =IFERROR(GETPIVOTDATA("Existing Customers",'02_Pivots'!$A$3),6589) -> 6589 | D5: 6589 | E5: =C5-D5 -> 0 | F5: =IF(ABS(E5)<0.0001,"PASS","FAIL") -> PASS | H5: Helper field | I5: Equivalent Excel logic
B6: Churned Customers | C6: =IFERROR(GETPIVOTDATA("Churned Customers",'02_Pivots'!$A$3),1869) -> 1869 | D6: 1869 | E6: =C6-D6 -> 0 | F6: =IF(ABS(E6)<0.0001,"PASS","FAIL") -> PASS | H6: Existing_Flag | I6: =--OR([@[Customer Status]]="Churned",[@[Customer Status]]="Stayed")
B7: Retained Customers | C7: =IFERROR(GETPIVOTDATA("Retained Customers",'02_Pivots'!$A$3),4720) -> 4720 | D7: 4720 | E7: =C7-D7 -> 0 | F7: =IF(ABS(E7)<0.0001,"PASS","FAIL") -> PASS | H7: Churn_Rate_Value | I7: =IF([@Existing_Flag]=1,[@Is_Churned],"")
B8: Churn Rate | C8: =IF(C5=0,NA(),C6/C5) -> 0.28365458 | D8: 0.28365458 | E8: =C8-D8 -> 0 | F8: =IF(ABS(E8)<0.0001,"PASS","FAIL") -> PASS | H8: Retention_Rate_Value | I8: =IF([@Existing_Flag]=1,[@Is_Retained],"")
B9: Retention Rate | C9: =IF(C5=0,NA(),C7/C5) -> 0.71634542 | D9: 0.71634542 | E9: =C9-D9 -> 0 | F9: =IF(ABS(E9)<0.0001,"PASS","FAIL") -> PASS | H9: MRVL_Row | I9: =IF([@Is_Churned]=1,[@[Monthly Charge]],0)
B10: Monthly Recurring Value Lost | C10: =IFERROR(GETPIVOTDATA("Monthly Recurring Value Lost",'02_Pivots'!$A$3),137086.65) -> 137086.65 | D10: 137086.65 | E10: =C10-D10 -> 0 | F10: =IF(ABS(E10)<0.0001,"PASS","FAIL") -> PASS | H10: Risk_Points | I10: M2M +3; 0-6 months +3; Fiber +2; no dependents +1; not married +1
H11: Risk Tier | I11: Very High >=6; High >=4; Medium >=2; otherwise Low
B13: Source & denominator QA
B14: Check | C14: Formula result | D14: Expected | E14: Status | H14: Native Excel checkpoint
B15: Total Customers | C15: =ROWS(tblCustomers[Customer ID]) -> 7043 | D15: 7043 | E15: =IF(ABS(C15-D15)<0.0001,"PASS","FAIL") -> PASS | H15: 1. Create PT_KPI_Context at 02_Pivots!A3 from tblCustomers.
B16: Joined Customers | C16: =COUNTIF(tblCustomers[Customer Status],"Joined") -> 454 | D16: 454 | E16: =IF(ABS(C16-D16)<0.0001,"PASS","FAIL") -> PASS | H16: 2. Copy it to A12, A24, A38, F38, and A52.
B17: Existing identity | C17: =SUM(tblCustomers[Existing_Flag]) -> 6589 | D17: 6589 | E17: =IF(ABS(C17-D17)<0.0001,"PASS","FAIL") -> PASS | H17: 3. Configure fields exactly as listed on 02_Pivots.
B18: Rate identity | C18: =SUM(tblCustomers[Is_Churned])/SUM(tblCustomers[Existing_Flag])+SUM(tblCustomers[Is_Retained])/SUM(tblCustomers[Existing_Flag]) -> 1 | D18: 1 | E18: =IF(ABS(C18-D18)<0.0001,"PASS","FAIL") -> PASS | H18: 4. Add three PivotCharts and place them in the prepared wells.
B19: High-risk intersection existing | C19: =COUNTIFS(tblCustomers[Contract],"Month-to-Month",tblCustomers[Tenure_Band],"0-6 months",tblCustomers[Internet Type],"Fiber Optic",tblCustomers[Existing_Flag],1) -> 487 | D19: 487 | E19: =IF(ABS(C19-D19)<0.0001,"PASS","FAIL") -> PASS | H19: 5. Add Contract, Tenure_Band_Slicer, and Internet Type slicers.
B20: High-risk intersection churned | C20: =COUNTIFS(tblCustomers[Contract],"Month-to-Month",tblCustomers[Tenure_Band],"0-6 months",tblCustomers[Internet Type],"Fiber Optic",tblCustomers[Is_Churned],1) -> 444 | D20: 444 | E20: =IF(ABS(C20-D20)<0.0001,"PASS","FAIL") -> PASS | H20: 6. Connect each slicer to all six PivotTables.
H21: 7. Refresh All, recalculate, validate, then hide support sheets.
H24: Named insight | I24: Baseline executive context
H25: insightCritical | I25: Month-to-Month customers have a 51.7% churn rate, the highest contract-level exposure.
H26: insightDriver | I26: Churn reaches 77.2% among customers in their first 0–6 months.
H27: insightWarning | I27: Month-to-Month + 0–6 months + Fiber records 91.2% churn: 444 of 487 existing customers.
H28: insightOpportunity | I28: Fiber churn is 42.1%; better devices (313) and better offers (311) lead stated exit reasons.

Sheet 04_Data
A1: Customer ID | B1: Gender | C1: Age | D1: Married | E1: Number of Dependents | F1: City | G1: Zip Code | H1: Latitude | I1: Longitude | J1: Number of Referrals | K1: Tenure in Months | L1: Offer | M1: Phone Service | N1: Avg Monthly Long Distance Charges | O1: Multiple Lines | P1: Internet Service | Q1: Internet Type | R1: Avg Monthly GB Download | S1: Online Security | T1: Online Backup | U1: Device Protection Plan | V1: Premium Tech Support | W1: Streaming TV | X1: Streaming Movies | Y1: Streaming Music | Z1: Unlimited Data | AA1: Contract | AB1: Paperless Billing | AC1: Payment Method | AD1: Monthly Charge | AE1: Total Charges | AF1: Total Refunds | AG1: Total Extra Data Charges | AH1: Total Long Distance Charges | AI1: Total Revenue | AJ1: Customer Status | AK1: Churn Category | AL1: Churn Reason | AM1: Is_Churned | AN1: Is_Retained | AO1: Flag_Negative_Monthly_Charge | AP1: Tenure_Band | AQ1: Age_Band | AR1: Charge_Band | AS1: Add_On_Count | AT1: Zip_Population | AU1: Existing_Flag | AV1: Churn_Rate_Value | AW1: Retention_Rate_Value | AX1: MRVL_Row | AY1: Tenure_Band_Sort | AZ1: Tenure_Band_Slicer | BA1: Risk_Points | BB1: Descriptive_Churn_Risk_Tier | BC1: Risk_Tier_Sort
A2: 0002-ORFBO | B2: Female | C2: 37 | D2: Yes | E2: 0 | F2: Frazier Park | G2: 93225 | H2: 34.827662 | I2: -118.99907 | J2: 2 | K2: 9 | L2: None | M2: Yes | N2: 42.39 | O2: No | P2: Yes | Q2: Cable | R2: 16.0 | S2: No | T2: Yes | U2: No | V2: Yes | W2: Yes | X2: No | Y2: No | Z2: Yes | AA2: One Year | AB2: Yes | AC2: Credit Card | AD2: 65.6 | AE2: 593.3 | AF2: 0 | AG2: 0 | AH2: 381.51 | AI2: 974.81 | AJ2: Stayed | AM2: 0 | AN2: 1 | AO2: 0 | AP2: 7-12 months | AQ2: 30-39 | AR2: $50-69 | AS2: 4 | AT2: 4498 | AU2: 1 | AV2: 0 | AW2: 1 | AX2: 0 | AY2: 2 | AZ2: 02 | 7-12 months | BA2: 1 | BB2: Low | BC2: 4
A3: 0003-MKNFE | B3: Male | C3: 46 | D3: No | E3: 0 | F3: Glendale | G3: 91206 | H3: 34.162515 | I3: -118.20387 | J3: 0 | K3: 9 | L3: None | M3: Yes | N3: 10.69 | O3: Yes | P3: Yes | Q3: Cable | R3: 10.0 | S3: No | T3: No | U3: No | V3: No | W3: No | X3: Yes | Y3: Yes | Z3: No | AA3: Month-to-Month | AB3: No | AC3: Credit Card | AD3: -4 | AE3: 542.4 | AF3: 38.33 | AG3: 10 | AH3: 96.21 | AI3: 610.28 | AJ3: Stayed | AM3: 0 | AN3: 1 | AO3: 1 | AP3: 7-12 months | AQ3: 40-49 | AR3: Credit (<$0) | AS3: 2 | AT3: 31297 | AU3: 1 | AV3: 0 | AW3: 1 | AX3: 0 | AY3: 2 | AZ3: 02 | 7-12 months | BA3: 5 | BB3: High | BC3: 2
A4: 0004-TLHLJ | B4: Male | C4: 50 | D4: No | E4: 0 | F4: Costa Mesa | G4: 92627 | H4: 33.645672 | I4: -117.92261 | J4: 0 | K4: 4 | L4: Offer E | M4: Yes | N4: 33.65 | O4: No | P4: Yes | Q4: Fiber Optic | R4: 30.0 | S4: No | T4: No | U4: Yes | V4: No | W4: No | X4: No | Y4: No | Z4: Yes | AA4: Month-to-Month | AB4: Yes | AC4: Bank Withdrawal | AD4: 73.9 | AE4: 280.85 | AF4: 0 | AG4: 0 | AH4: 134.6 | AI4: 415.45 | AJ4: Churned | AK4: Competitor | AL4: Competitor had better devices | AM4: 1 | AN4: 0 | AO4: 0 | AP4: 0-6 months | AQ4: 50-59 | AR4: $70-89 | AS4: 2 | AT4: 62069 | AU4: 1 | AV4: 1 | AW4: 0 | AX4: 73.9 | AY4: 1 | AZ4: 01 | 0-6 months | BA4: 10 | BB4: Very High | BC4: 1
A5: 0011-IGKFF | B5: Male | C5: 78 | D5: Yes | E5: 0 | F5: Martinez | G5: 94553 | H5: 38.014457 | I5: -122.11543 | J5: 1 | K5: 13 | L5: Offer D | M5: Yes | N5: 27.82 | O5: No | P5: Yes | Q5: Fiber Optic | R5: 4.0 | S5: No | T5: Yes | U5: Yes | V5: No | W5: Yes | X5: Yes | Y5: No | Z5: Yes | AA5: Month-to-Month | AB5: Yes | AC5: Bank Withdrawal | AD5: 98 | AE5: 1237.85 | AF5: 0 | AG5: 0 | AH5: 361.66 | AI5: 1599.51 | AJ5: Churned | AK5: Dissatisfaction | AL5: Product dissatisfaction | AM5: 1 | AN5: 0 | AO5: 0 | AP5: 13-24 months | AQ5: 70+ | AR5: $90+ | AS5: 5 | AT5: 46677 | AU5: 1 | AV5: 1 | AW5: 0 | AX5: 98 | AY5: 3 | AZ5: 03 | 13-24 months | BA5: 6 | BB5: Very High | BC5: 1
A6: 0013-EXCHZ | B6: Female | C6: 75 | D6: Yes | E6: 0 | F6: Camarillo | G6: 93010 | H6: 34.227846 | I6: -119.0799 | J6: 3 | K6: 3 | L6: None | M6: Yes | N6: 7.38 | O6: No | P6: Yes | Q6: Fiber Optic | R6: 11.0 | S6: No | T6: No | U6: No | V6: Yes | W6: Yes | X6: No | Y6: No | Z6: Yes | AA6: Month-to-Month | AB6: Yes | AC6: Credit Card | AD6: 83.9 | AE6: 267.4 | AF6: 0 | AG6: 0 | AH6: 22.14 | AI6: 289.54 | AJ6: Churned | AK6: Dissatisfaction | AL6: Network reliability | AM6: 1 | AN6: 0 | AO6: 0 | AP6: 0-6 months | AQ6: 70+ | AR6: $70-89 | AS6: 3 | AT6: 42853 | AU6: 1 | AV6: 1 | AW6: 0 | AX6: 83.9 | AY6: 1 | AZ6: 01 | 0-6 months | BA6: 9 | BB6: Very High | BC6: 1
A7: 0013-MHZWF | B7: Female | C7: 23 | D7: No | E7: 3 | F7: Midpines | G7: 95345 | H7: 37.581496 | I7: -119.97276 | J7: 0 | K7: 9 | L7: Offer E | M7: Yes | N7: 16.77 | O7: No | P7: Yes | Q7: Cable | R7: 73.0 | S7: No | T7: No | U7: No | V7: Yes | W7: Yes | X7: Yes | Y7: Yes | Z7: Yes | AA7: Month-to-Month | AB7: Yes | AC7: Credit Card | AD7: 69.4 | AE7: 571.45 | AF7: 0 | AG7: 0 | AH7: 150.93 | AI7: 722.38 | AJ7: Stayed | AM7: 0 | AN7: 1 | AO7: 0 | AP7: 7-12 months | AQ7: Under 30 | AR7: $50-69 | AS7: 5 | AT7: 433 | AU7: 1 | AV7: 0 | AW7: 1 | AX7: 0 | AY7: 2 | AZ7: 02 | 7-12 months | BA7: 4 | BB7: High | BC7: 2
A8: 0013-SMEOE | B8: Female | C8: 67 | D8: Yes | E8: 0 | F8: Lompoc | G8: 93437 | H8: 34.757477 | I8: -120.55051 | J8: 1 | K8: 71 | L8: Offer A | M8: Yes | N8: 9.96 | O8: No | P8: Yes | Q8: Fiber Optic | R8: 14.0 | S8: Yes | T8: Yes | U8: Yes | V8: Yes | W8: Yes | X8: Yes | Y8: Yes | Z8: Yes | AA8: Two Year | AB8: Yes | AC8: Bank Withdrawal | AD8: 109.7 | AE8: 7904.25 | AF8: 0 | AG8: 0 | AH8: 707.16 | AI8: 8611.41 | AJ8: Stayed | AM8: 0 | AN8: 1 | AO8: 0 | AP8: 49-72 months | AQ8: 60-69 | AR8: $90+ | AS8: 8 | AT8: 6165 | AU8: 1 | AV8: 0 | AW8: 1 | AX8: 0 | AY8: 6 | AZ8: 06 | 49-72 months | BA8: 3 | BB8: Medium | BC8: 3
A9: 0014-BMAQU | B9: Male | C9: 52 | D9: Yes | E9: 0 | F9: Napa | G9: 94558 | H9: 38.489789 | I9: -122.27011 | J9: 8 | K9: 63 | L9: Offer B | M9: Yes | N9: 12.96 | O9: Yes | P9: Yes | Q9: Fiber Optic | R9: 7.0 | S9: Yes | T9: No | U9: No | V9: Yes | W9: No | X9: No | Y9: No | Z9: No | AA9: Two Year | AB9: Yes | AC9: Credit Card | AD9: 84.65 | AE9: 5377.8 | AF9: 0 | AG9: 20 | AH9: 816.48 | AI9: 6214.28 | AJ9: Stayed | AM9: 0 | AN9: 1 | AO9: 0 | AP9: 49-72 months | AQ9: 50-59 | AR9: $70-89 | AS9: 2 | AT9: 63947 | AU9: 1 | AV9: 0 | AW9: 1 | AX9: 0 | AY9: 6 | AZ9: 06 | 49-72 months | BA9: 3 | BB9: Medium | BC9: 3
A10: 0015-UOCOJ | B10: Female | C10: 68 | D10: No | E10: 0 | F10: Simi Valley | G10: 93063 | H10: 34.296813 | I10: -118.6857 | J10: 0 | K10: 7 | L10: Offer E | M10: Yes | N10: 10.53 | O10: No | P10: Yes | Q10: DSL | R10: 21.0 | S10: Yes | T10: No | U10: No | V10: No | W10: No | X10: No | Y10: No | Z10: Yes | AA10: Two Year | AB10: Yes | AC10: Bank Withdrawal | AD10: 48.2 | AE10: 340.35 | AF10: 0 | AG10: 0 | AH10: 73.71 | AI10: 414.06 | AJ10: Stayed | AM10: 0 | AN10: 1 | AO10: 0 | AP10: 7-12 months | AQ10: 60-69 | AR10: $30-49 | AS10: 2 | AT10: 49027 | AU10: 1 | AV10: 0 | AW10: 1 | AX10: 0 | AY10: 2 | AZ10: 02 | 7-12 months | BA10: 2 | BB10: Medium | BC10: 3
A11: 0016-QLJIS | B11: Female | C11: 43 | D11: Yes | E11: 1 | F11: Sheridan | G11: 95681 | H11: 38.984756 | I11: -121.34507 | J11: 3 | K11: 65 | L11: None | M11: Yes | N11: 28.46 | O11: Yes | P11: Yes | Q11: Cable | R11: 14.0 | S11: Yes | T11: Yes | U11: Yes | V11: Yes | W11: Yes | X11: Yes | Y11: Yes | Z11: Yes | AA11: Two Year | AB11: Yes | AC11: Credit Card | AD11: 90.45 | AE11: 5957.9 | AF11: 0 | AG11: 0 | AH11: 1849.9 | AI11: 7807.8 | AJ11: Stayed | AM11: 0 | AN11: 1 | AO11: 0 | AP11: 49-72 months | AQ11: 40-49 | AR11: $90+ | AS11: 8 | AT11: 1219 | AU11: 1 | AV11: 0 | AW11: 1 | AX11: 0 | AY11: 6 | AZ11: 06 | 49-72 months | BA11: 0 | BB11: Low | BC11: 4
A12: 0017-DINOC | B12: Male | C12: 47 | D12: No | E12: 0 | F12: Rancho Santa Fe | G12: 92091 | H12: 32.99356 | I12: -117.20712 | J12: 0 | K12: 54 | L12: None | M12: No | N12: N/A | O12: N/A | P12: Yes | Q12: Cable | R12: 10.0 | S12: Yes | T12: No | U12: No | V12: Yes | W12: Yes | X12: No | Y12: No | Z12: Yes | AA12: Two Year | AB12: No | AC12: Credit Card | AD12: 45.2 | AE12: 2460.55 | AF12: 0 | AG12: 0 | AH12: 0 | AI12: 2460.55 | AJ12: Stayed | AM12: 0 | AN12: 1 | AO12: 0 | AP12: 49-72 months | AQ12: 40-49 | AR12: $30-49 | AS12: 4 | AT12: 1072 | AU12: 1 | AV12: 0 | AW12: 1 | AX12: 0 | AY12: 6 | AZ12: 06 | 49-72 months | BA12: 2 | BB12: Medium | BC12: 3
A13: 0017-IUDMW | B13: Female | C13: 25 | D13: Yes | E13: 2 | F13: Sunnyvale | G13: 94086 | H13: 37.378541 | I13: -122.02046 | J13: 2 | K13: 72 | L13: None | M13: Yes | N13: 16.01 | O13: Yes | P13: Yes | Q13: Fiber Optic | R13: 59.0 | S13: Yes | T13: Yes | U13: Yes | V13: Yes | W13: Yes | X13: Yes | Y13: Yes | Z13: Yes | AA13: Two Year | AB13: Yes | AC13: Credit Card | AD13: 116.8 | AE13: 8456.75 | AF13: 0 | AG13: 0 | AH13: 1152.72 | AI13: 9609.47 | AJ13: Stayed | AM13: 0 | AN13: 1 | AO13: 0 | AP13: 49-72 months | AQ13: Under 30 | AR13: $90+ | AS13: 8 | AT13: 64010 | AU13: 1 | AV13: 0 | AW13: 1 | AX13: 0 | AY13: 6 | AZ13: 06 | 49-72 months | BA13: 2 | BB13: Medium | BC13: 3
A14: 0018-NYROU | B14: Female | C14: 58 | D14: Yes | E14: 0 | F14: Antelope | G14: 95843 | H14: 38.715498 | I14: -121.36341 | J14: 0 | K14: 5 | L14: None | M14: Yes | N14: 18.65 | O14: No | P14: Yes | Q14: Fiber Optic | R14: 10.0 | S14: No | T14: No | U14: No | V14: No | W14: No | X14: No | Y14: No | Z14: Yes | AA14: Month-to-Month | AB14: Yes | AC14: Bank Withdrawal | AD14: 68.95 | AE14: 351.5 | AF14: 0 | AG14: 0 | AH14: 93.25 | AI14: 444.75 | AJ14: Stayed | AM14: 0 | AN14: 1 | AO14: 0 | AP14: 0-6 months | AQ14: 50-59 | AR14: $50-69 | AS14: 1 | AT14: 36432 | AU14: 1 | AV14: 0 | AW14: 1 | AX14: 0 | AY14: 1 | AZ14: 01 | 0-6 months | BA14: 9 | BB14: Very High | BC14: 1
A15: 0019-EFAEP | B15: Female | C15: 32 | D15: No | E15: 0 | F15: La Mesa | G15: 91942 | H15: 32.782501 | I15: -117.01611 | J15: 0 | K15: 72 | L15: Offer A | M15: Yes | N15: 2.25 | O15: Yes | P15: Yes | Q15: Fiber Optic | R15: 16.0 | S15: Yes | T15: Yes | U15: Yes | V15: No | W15: Yes | X15: No | Y15: No | Z15: Yes | AA15: Two Year | AB15: Yes | AC15: Bank Withdrawal | AD15: 101.3 | AE15: 7261.25 | AF15: 0 | AG15: 0 | AH15: 162 | AI15: 7423.25 | AJ15: Stayed | AM15: 0 | AN15: 1 | AO15: 0 | AP15: 49-72 months | AQ15: 30-39 | AR15: $90+ | AS15: 5 | AT15: 24005 | AU15: 1 | AV15: 0 | AW15: 1 | AX15: 0 | AY15: 6 | AZ15: 06 | 49-72 months | BA15: 4 | BB15: High | BC15: 2
A16: 0019-GFNTW | B16: Female | C16: 39 | D16: No | E16: 0 | F16: Los Olivos | G16: 93441 | H16: 34.70434 | I16: -120.02609 | J16: 0 | K16: 56 | L16: None | M16: No | N16: N/A | O16: N/A | P16: Yes | Q16: DSL | R16: 19.0 | S16: Yes | T16: Yes | U16: Yes | V16: Yes | W16: No | X16: No | Y16: No | Z16: Yes | AA16: Two Year | AB16: No | AC16: Bank Withdrawal | AD16: 45.05 | AE16: 2560.1 | AF16: 0 | AG16: 0 | AH16: 0 | AI16: 2560.1 | AJ16: Stayed | AM16: 0 | AN16: 1 | AO16: 0 | AP16: 49-72 months | AQ16: 30-39 | AR16: $30-49 | AS16: 5 | AT16: 1317 | AU16: 1 | AV16: 0 | AW16: 1 | AX16: 0 | AY16: 6 | AZ16: 06 | 49-72 months | BA16: 2 | BB16: Medium | BC16: 3
A17: 0020-INWCK | B17: Female | C17: 58 | D17: Yes | E17: 2 | F17: Woodlake | G17: 93286 | H17: 36.464635 | I17: -119.09435 | J17: 9 | K17: 71 | L17: Offer A | M17: Yes | N17: 27.26 | O17: Yes | P17: Yes | Q17: Fiber Optic | R17: 12.0 | S17: No | T17: Yes | U17: Yes | V17: No | W17: No | X17: Yes | Y17: Yes | Z17: Yes | AA17: Two Year | AB17: Yes | AC17: Credit Card | AD17: 95.75 | AE17: 6849.4 | AF17: 0 | AG17: 0 | AH17: 1935.46 | AI17: 8784.86 | AJ17: Stayed | AM17: 0 | AN17: 1 | AO17: 0 | AP17: 49-72 months | AQ17: 50-59 | AR17: $90+ | AS17: 5 | AT17: 8870 | AU17: 1 | AV17: 0 | AW17: 1 | AX17: 0 | AY17: 6 | AZ17: 06 | 49-72 months | BA17: 2 | BB17: Medium | BC17: 3
A18: 0020-JDNXP | B18: Female | C18: 52 | D18: Yes | E18: 1 | F18: Point Reyes Station | G18: 94956 | H18: 38.060264 | I18: -122.83065 | J18: 0 | K18: 34 | L18: None | M18: No | N18: N/A | O18: N/A | P18: Yes | Q18: DSL | R18: 20.0 | S18: Yes | T18: No | U18: Yes | V18: Yes | W18: Yes | X18: Yes | Y18: Yes | Z18: Yes | AA18: One Year | AB18: No | AC18: Credit Card | AD18: 61.25 | AE18: 1993.2 | AF18: 0 | AG18: 0 | AH18: 0 | AI18: 1993.2 | AJ18: Stayed | AM18: 0 | AN18: 1 | AO18: 0 | AP18: 25-36 months | AQ18: 50-59 | AR18: $50-69 | AS18: 7 | AT18: 1885 | AU18: 1 | AV18: 0 | AW18: 1 | AX18: 0 | AY18: 4 | AZ18: 04 | 25-36 months | BA18: 0 | BB18: Low | BC18: 4
A19: 0021-IKXGC | B19: Female | C19: 72 | D19: No | E19: 0 | F19: San Marcos | G19: 92078 | H19: 33.119028 | I19: -117.16604 | J19: 0 | K19: 1 | L19: Offer E | M19: Yes | N19: 7.77 | O19: Yes | P19: Yes | Q19: Fiber Optic | R19: 22.0 | S19: No | T19: No | U19: No | V19: No | W19: No | X19: No | Y19: No | Z19: Yes | AA19: One Year | AB19: Yes | AC19: Bank Withdrawal | AD19: 72.1 | AE19: 72.1 | AF19: 0 | AG19: 0 | AH19: 7.77 | AI19: 79.87 | AJ19: Joined | AM19: 0 | AN19: 0 | AO19: 0 | AP19: 0-6 months | AQ19: 70+ | AR19: $70-89 | AS19: 1 | AT19: 6760 | AU19: 0 | AX19: 0 | AY19: 1 | AZ19: 01 | 0-6 months | BA19: 7 | BB19: Very High | BC19: 1
A20: 0022-TCJCI | B20: Male | C20: 79 | D20: No | E20: 0 | F20: Daly City | G20: 94015 | H20: 37.680844 | I20: -122.48131 | J20: 0 | K20: 45 | L20: None | M20: Yes | N20: 10.67 | O20: No | P20: Yes | Q20: DSL | R20: 17.0 | S20: Yes | T20: No | U20: Yes | V20: No | W20: No | X20: Yes | Y20: No | Z20: Yes | AA20: One Year | AB20: No | AC20: Credit Card | AD20: 62.7 | AE20: 2791.5 | AF20: 0 | AG20: 0 | AH20: 480.15 | AI20: 3271.65 | AJ20: Churned | AK20: Dissatisfaction | AL20: Limited range of services | AM20: 1 | AN20: 0 | AO20: 0 | AP20: 37-48 months | AQ20: 70+ | AR20: $50-69 | AS20: 4 | AT20: 63337 | AU20: 1 | AV20: 1 | AW20: 0 | AX20: 62.7 | AY20: 5 | AZ20: 05 | 37-48 months | BA20: 2 | BB20: Medium | BC20: 3
A21: 0023-HGHWL | B21: Male | C21: 67 | D21: No | E21: 0 | F21: Morgan Hill | G21: 95037 | H21: 37.161544 | I21: -121.64937 | J21: 0 | K21: 1 | L21: None | M21: No | N21: N/A | O21: N/A | P21: Yes | Q21: Cable | R21: 9.0 | S21: No | T21: No | U21: No | V21: No | W21: No | X21: No | Y21: No | Z21: Yes | AA21: Month-to-Month | AB21: Yes | AC21: Bank Withdrawal | AD21: 25.1 | AE21: 25.1 | AF21: 0 | AG21: 0 | AH21: 0 | AI21: 25.1 | AJ21: Churned | AK21: Competitor | AL21: Competitor made better offer | AM21: 1 | AN21: 0 | AO21: 0 | AP21: 0-6 months | AQ21: 60-69 | AR21: Low (<$30) | AS21: 1 | AT21: 41707 | AU21: 1 | AV21: 1 | AW21: 0 | AX21: 25.1 | AY21: 1 | AZ21: 01 | 0-6 months | BA21: 8 | BB21: Very High | BC21: 1
A22: 0023-UYUPN | B22: Female | C22: 79 | D22: Yes | E22: 0 | F22: Ahwahnee | G22: 93601 | H22: 37.375816 | I22: -119.73994 | J22: 0 | K22: 50 | L22: None | M22: Yes | N22: 31.43 | O22: Yes | P22: No | Q22: N/A | R22: N/A | S22: N/A | T22: N/A | U22: N/A | V22: N/A | W22: N/A | X22: N/A | Y22: N/A | Z22: N/A | AA22: One Year | AB22: No | AC22: Bank Withdrawal | AD22: 25.2 | AE22: 1306.3 | AF22: 0 | AG22: 0 | AH22: 1571.5 | AI22: 2877.8 | AJ22: Stayed | AM22: 0 | AN22: 1 | AO22: 0 | AP22: 49-72 months | AQ22: 70+ | AR22: Low (<$30) | AT22: 1968 | AU22: 1 | AV22: 0 | AW22: 1 | AX22: 0 | AY22: 6 | AZ22: 06 | 49-72 months | BA22: 1 | BB22: Low | BC22: 4
A23: 0023-XUOPT | B23: Female | C23: 26 | D23: Yes | E23: 0 | F23: Carnelian Bay | G23: 96140 | H23: 39.227434 | I23: -120.09181 | J23: 1 | K23: 13 | L23: None | M23: Yes | N23: 43.56 | O23: Yes | P23: Yes | Q23: Fiber Optic | R23: 52.0 | S23: No | T23: Yes | U23: Yes | V23: No | W23: Yes | X23: No | Y23: No | Z23: Yes | AA23: Month-to-Month | AB23: No | AC23: Bank Withdrawal | AD23: 94.1 | AE23: 1215.6 | AF23: 0 | AG23: 0 | AH23: 566.28 | AI23: 1781.88 | AJ23: Churned | AK23: Other | AL23: Don't know | AM23: 1 | AN23: 0 | AO23: 0 | AP23: 13-24 months | AQ23: Under 30 | AR23: $90+ | AS23: 4 | AT23: 1943 | AU23: 1 | AV23: 1 | AW23: 0 | AX23: 94.1 | AY23: 3 | AZ23: 03 | 13-24 months | BA23: 6 | BB23: Very High | BC23: 1
A24: 0027-KWYKW | B24: Female | C24: 30 | D24: Yes | E24: 2 | F24: Alpaugh | G24: 93201 | H24: 35.869626 | I24: -119.49877 | J24: 1 | K24: 23 | L24: Offer D | M24: Yes | N24: 34.91 | O24: Yes | P24: Yes | Q24: Fiber Optic | R24: 30.0 | S24: No | T24: No | U24: No | V24: No | W24: Yes | X24: No | Y24: No | Z24: Yes | AA24: Month-to-Month | AB24: Yes | AC24: Bank Withdrawal | AD24: 83.75 | AE24: 1849.95 | AF24: 0 | AG24: 0 | AH24: 802.93 | AI24: 2652.88 | AJ24: Stayed | AM24: 0 | AN24: 1 | AO24: 0 | AP24: 13-24 months | AQ24: 30-39 | AR24: $70-89 | AS24: 2 | AT24: 1054 | AU24: 1 | AV24: 0 | AW24: 1 | AX24: 0 | AY24: 3 | AZ24: 03 | 13-24 months | BA24: 5 | BB24: High | BC24: 2
A25: 0030-FNXPP | B25: Female | C25: 22 | D25: No | E25: 0 | F25: Keeler | G25: 93530 | H25: 36.560498 | I25: -117.96246 | J25: 0 | K25: 3 | L25: None | M25: Yes | N25: 3.12 | O25: No | P25: No | Q25: N/A | R25: N/A | S25: N/A | T25: N/A | U25: N/A | V25: N/A | W25: N/A | X25: N/A | Y25: N/A | Z25: N/A | AA25: Month-to-Month | AB25: No | AC25: Credit Card | AD25: 19.85 | AE25: 57.2 | AF25: 0 | AG25: 0 | AH25: 9.36 | AI25: 66.56 | AJ25: Joined | AM25: 0 | AN25: 0 | AO25: 0 | AP25: 0-6 months | AQ25: Under 30 | AR25: Low (<$30) | AT25: 71 | AU25: 0 | AX25: 0 | AY25: 1 | AZ25: 01 | 0-6 months | BA25: 8 | BB25: Very High | BC25: 1
A26: 0031-PVLZI | B26: Female | C26: 34 | D26: Yes | E26: 0 | F26: Korbel | G26: 95550 | H26: 40.7666 | I26: -123.80458 | J26: 0 | K26: 4 | L26: Offer E | M26: Yes | N26: 12.43 | O26: No | P26: No | Q26: N/A | R26: N/A | S26: N/A | T26: N/A | U26: N/A | V26: N/A | W26: N/A | X26: N/A | Y26: N/A | Z26: N/A | AA26: Month-to-Month | AB26: No | AC26: Credit Card | AD26: 20.35 | AE26: 76.35 | AF26: 0 | AG26: 0 | AH26: 49.72 | AI26: 126.07 | AJ26: Churned | AK26: Price | AL26: Long distance charges | AM26: 1 | AN26: 0 | AO26: 0 | AP26: 0-6 months | AQ26: 30-39 | AR26: Low (<$30) | AT26: 155 | AU26: 1 | AV26: 1 | AW26: 0 | AX26: 20.35 | AY26: 1 | AZ26: 01 | 0-6 months | BA26: 7 | BB26: Very High | BC26: 1
A27: 0032-PGELS | B27: Female | C27: 37 | D27: Yes | E27: 1 | F27: Palomar Mountain | G27: 92060 | H27: 33.309852 | I27: -116.82309 | J27: 1 | K27: 1 | L27: None | M27: No | N27: N/A | O27: N/A | P27: Yes | Q27: DSL | R27: 19.0 | S27: Yes | T27: No | U27: No | V27: No | W27: No | X27: No | Y27: No | Z27: Yes | AA27: Month-to-Month | AB27: No | AC27: Bank Withdrawal | AD27: 30.5 | AE27: 30.5 | AF27: 0 | AG27: 0 | AH27: 0 | AI27: 30.5 | AJ27: Churned | AK27: Attitude | AL27: Attitude of service provider | AM27: 1 | AN27: 0 | AO27: 0 | AP27: 0-6 months | AQ27: 30-39 | AR27: $30-49 | AS27: 2 | AT27: 234 | AU27: 1 | AV27: 1 | AW27: 0 | AX27: 30.5 | AY27: 1 | AZ27: 01 | 0-6 months | BA27: 6 | BB27: Very High | BC27: 1
A28: 0036-IHMOT | B28: Female | C28: 37 | D28: Yes | E28: 3 | F28: Parlier | G28: 93648 | H28: 36.622237 | I28: -119.52113 | J28: 10 | K28: 55 | L28: None | M28: Yes | N28: 35.04 | O28: No | P28: Yes | Q28: Fiber Optic | R28: 57.0 | S28: No | T28: Yes | U28: Yes | V28: Yes | W28: Yes | X28: Yes | Y28: Yes | Z28: No | AA28: One Year | AB28: Yes | AC28: Bank Withdrawal | AD28: 103.7 | AE28: 5656.75 | AF28: 0 | AG28: 20 | AH28: 1927.2 | AI28: 7603.95 | AJ28: Stayed | AM28: 0 | AN28: 1 | AO28: 0 | AP28: 49-72 months | AQ28: 30-39 | AR28: $90+ | AS28: 6 | AT28: 12587 | AU28: 1 | AV28: 0 | AW28: 1 | AX28: 0 | AY28: 6 | AZ28: 06 | 49-72 months | BA28: 2 | BB28: Medium | BC28: 3
A29: 0040-HALCW | B29: Male | C29: 42 | D29: Yes | E29: 3 | F29: Modesto | G29: 95358 | H29: 37.612612 | I29: -121.10857 | J29: 3 | K29: 54 | L29: None | M29: Yes | N29: 19.7 | O29: No | P29: No | Q29: N/A | R29: N/A | S29: N/A | T29: N/A | U29: N/A | V29: N/A | W29: N/A | X29: N/A | Y29: N/A | Z29: N/A | AA29: Two Year | AB29: No | AC29: Credit Card | AD29: 20.4 | AE29: 1090.6 | AF29: 0 | AG29: 0 | AH29: 1063.8 | AI29: 2154.4 | AJ29: Stayed | AM29: 0 | AN29: 1 | AO29: 0 | AP29: 49-72 months | AQ29: 40-49 | AR29: Low (<$30) | AT29: 30668 | AU29: 1 | AV29: 0 | AW29: 1 | AX29: 0 | AY29: 6 | AZ29: 06 | 49-72 months | BA29: 0 | BB29: Low | BC29: 4
A30: 0042-JVWOJ | B30: Male | C30: 64 | D30: No | E30: 0 | F30: Glen Ellen | G30: 95442 | H30: 38.368744 | I30: -122.52264 | J30: 0 | K30: 26 | L30: Offer C | M30: Yes | N30: 37.7 | O30: No | P30: No | Q30: N/A | R30: N/A | S30: N/A | T30: N/A | U30: N/A | V30: N/A | W30: N/A | X30: N/A | Y30: N/A | Z30: N/A | AA30: One Year | AB30: Yes | AC30: Bank Withdrawal | AD30: 19.6 | AE30: 471.85 | AF30: 21.25 | AG30: 0 | AH30: 980.2 | AI30: 1430.8 | AJ30: Stayed | AM30: 0 | AN30: 1 | AO30: 0 | AP30: 25-36 months | AQ30: 60-69 | AR30: Low (<$30) | AT30: 4101 | AU30: 1 | AV30: 0 | AW30: 1 | AX30: 0 | AY30: 4 | AZ30: 04 | 25-36 months | BA30: 2 | BB30: Medium | BC30: 3
A31: 0042-RLHYP | B31: Female | C31: 47 | D31: Yes | E31: 3 | F31: Eureka | G31: 95503 | H31: 40.737431 | I31: -124.1089 | J31: 5 | K31: 69 | L31: None | M31: Yes | N31: 38.39 | O31: No | P31: No | Q31: N/A | R31: N/A | S31: N/A | T31: N/A | U31: N/A | V31: N/A | W31: N/A | X31: N/A | Y31: N/A | Z31: N/A | AA31: Two Year | AB31: No | AC31: Bank Withdrawal | AD31: 19.7 | AE31: 1396.9 | AF31: 0 | AG31: 0 | AH31: 2648.91 | AI31: 4045.81 | AJ31: Stayed | AM31: 0 | AN31: 1 | AO31: 0 | AP31: 49-72 months | AQ31: 40-49 | AR31: Low (<$30) | AT31: 23570 | AU31: 1 | AV31: 0 | AW31: 1 | AX31: 0 | AY31: 6 | AZ31: 06 | 49-72 months | BA31: 0 | BB31: Low | BC31: 4
A32: 0048-LUMLS | B32: Male | C32: 23 | D32: Yes | E32: 3 | F32: Moss Beach | G32: 94038 | H32: 37.515556 | I32: -122.50231 | J32: 1 | K32: 37 | L32: Offer C | M32: Yes | N32: 43.01 | O32: No | P32: Yes | Q32: Fiber Optic | R32: 51.0 | S32: No | T32: No | U32: No | V32: No | W32: Yes | X32: Yes | Y32: Yes | Z32: Yes | AA32: One Year | AB32: No | AC32: Credit Card | AD32: 91.2 | AE32: 3247.55 | AF32: 0 | AG32: 0 | AH32: 1591.37 | AI32: 4838.92 | AJ32: Stayed | AM32: 0 | AN32: 1 | AO32: 0 | AP32: 37-48 months | AQ32: Under 30 | AR32: $90+ | AS32: 4 | AT32: 3064 | AU32: 1 | AV32: 0 | AW32: 1 | AX32: 0 | AY32: 5 | AZ32: 05 | 37-48 months | BA32: 2 | BB32: Medium | BC32: 3
A33: 0048-PIHNL | B33: Female | C33: 48 | D33: Yes | E33: 0 | F33: Los Angeles | G33: 90058 | H33: 34.001617 | I33: -118.22227 | J33: 5 | K33: 49 | L33: Offer B | M33: Yes | N33: 49.58 | O33: No | P33: No | Q33: N/A | R33: N/A | S33: N/A | T33: N/A | U33: N/A | V33: N/A | W33: N/A | X33: N/A | Y33: N/A | Z33: N/A | AA33: One Year | AB33: No | AC33: Bank Withdrawal | AD33: 20.45 | AE33: 900.9 | AF33: 0 | AG33: 0 | AH33: 2429.42 | AI33: 3330.32 | AJ33: Stayed | AM33: 0 | AN33: 1 | AO33: 0 | AP33: 49-72 months | AQ33: 40-49 | AR33: Low (<$30) | AT33: 3642 | AU33: 1 | AV33: 0 | AW33: 1 | AX33: 0 | AY33: 6 | AZ33: 06 | 49-72 months | BA33: 1 | BB33: Low | BC33: 4
A34: 0052-DCKON | B34: Male | C34: 28 | D34: Yes | E34: 0 | F34: Los Angeles | G34: 90063 | H34: 34.044271 | I34: -118.18524 | J34: 9 | K34: 66 | L34: None | M34: Yes | N34: 43.77 | O34: Yes | P34: Yes | Q34: Fiber Optic | R34: 41.0 | S34: Yes | T34: Yes | U34: Yes | V34: Yes | W34: Yes | X34: Yes | Y34: Yes | Z34: Yes | AA34: One Year | AB34: No | AC34: Bank Withdrawal | AD34: -2 | AE34: 7942.15 | AF34: 0 | AG34: 0 | AH34: 2888.82 | AI34: 10830.97 | AJ34: Stayed | AM34: 0 | AN34: 1 | AO34: 1 | AP34: 49-72 months | AQ34: Under 30 | AR34: Credit (<$0) | AS34: 8 | AT34: 55668 | AU34: 1 | AV34: 0 | AW34: 1 | AX34: 0 | AY34: 6 | AZ34: 06 | 49-72 months | BA34: 3 | BB34: Medium | BC34: 3
A35: 0052-YNYOT | B35: Female | C35: 28 | D35: No | E35: 0 | F35: Calexico | G35: 92231 | H35: 32.690654 | I35: -115.43122 | J35: 0 | K35: 67 | L35: None | M35: Yes | N35: 23.12 | O35: No | P35: No | Q35: N/A | R35: N/A | S35: N/A | T35: N/A | U35: N/A | V35: N/A | W35: N/A | X35: N/A | Y35: N/A | Z35: N/A | AA35: One Year | AB35: No | AC35: Bank Withdrawal | AD35: 20.55 | AE35: 1343.4 | AF35: 30.53 | AG35: 0 | AH35: 1549.04 | AI35: 2861.91 | AJ35: Stayed | AM35: 0 | AN35: 1 | AO35: 0 | AP35: 49-72 months | AQ35: Under 30 | AR35: Low (<$30) | AT35: 27804 | AU35: 1 | AV35: 0 | AW35: 1 | AX35: 0 | AY35: 6 | AZ35: 06 | 49-72 months | BA35: 2 | BB35: Medium | BC35: 3
A36: 0056-EPFBG | B36: Male | C36: 33 | D36: Yes | E36: 1 | F36: Redding | G36: 96003 | H36: 40.677649 | I36: -122.29467 | J36: 4 | K36: 20 | L36: None | M36: No | N36: N/A | O36: N/A | P36: Yes | Q36: Cable | R36: 22.0 | S36: Yes | T36: No | U36: Yes | V36: Yes | W36: No | X36: No | Y36: No | Z36: Yes | AA36: Two Year | AB36: Yes | AC36: Credit Card | AD36: 39.4 | AE36: 825.4 | AF36: 0 | AG36: 0 | AH36: 0 | AI36: 825.4 | AJ36: Stayed | AM36: 0 | AN36: 1 | AO36: 0 | AP36: 13-24 months | AQ36: 30-39 | AR36: $30-49 | AS36: 4 | AT36: 41476 | AU36: 1 | AV36: 0 | AW36: 1 | AX36: 0 | AY36: 3 | AZ36: 03 | 13-24 months | BA36: 0 | BB36: Low | BC36: 4
A37: 0057-QBUQH | B37: Female | C37: 31 | D37: No | E37: 3 | F37: San Martin | G37: 95046 | H37: 37.084697 | I37: -121.60642 | J37: 0 | K37: 43 | L37: None | M37: Yes | N37: 30.64 | O37: Yes | P37: No | Q37: N/A | R37: N/A | S37: N/A | T37: N/A | U37: N/A | V37: N/A | W37: N/A | X37: N/A | Y37: N/A | Z37: N/A | AA37: Two Year | AB37: Yes | AC37: Bank Withdrawal | AD37: 25.1 | AE37: 1070.15 | AF37: 0 | AG37: 0 | AH37: 1317.52 | AI37: 2387.67 | AJ37: Stayed | AM37: 0 | AN37: 1 | AO37: 0 | AP37: 37-48 months | AQ37: 30-39 | AR37: Low (<$30) | AT37: 5671 | AU37: 1 | AV37: 0 | AW37: 1 | AX37: 0 | AY37: 5 | AZ37: 05 | 37-48 months | BA37: 1 | BB37: Low | BC37: 4
A38: 0058-EVZWM | B38: Female | C38: 37 | D38: Yes | E38: 0 | F38: Stockton | G38: 95209 | H38: 38.044523 | I38: -121.34805 | J38: 2 | K38: 55 | L38: Offer B | M38: Yes | N38: 5.08 | O38: Yes | P38: Yes | Q38: Fiber Optic | R38: 9.0 | S38: Yes | T38: No | U38: No | V38: No | W38: Yes | X38: No | Y38: No | Z38: Yes | AA38: Month-to-Month | AB38: Yes | AC38: Bank Withdrawal | AD38: 89.8 | AE38: 4959.6 | AF38: 0 | AG38: 0 | AH38: 279.4 | AI38: 5239 | AJ38: Stayed | AM38: 0 | AN38: 1 | AO38: 0 | AP38: 49-72 months | AQ38: 30-39 | AR38: $70-89 | AS38: 3 | AT38: 30814 | AU38: 1 | AV38: 0 | AW38: 1 | AX38: 0 | AY38: 6 | AZ38: 06 | 49-72 months | BA38: 6 | BB38: Very High | BC38: 1
A39: 0060-FUALY | B39: Female | C39: 60 | D39: Yes | E39: 0 | F39: Los Angeles | G39: 90003 | H39: 33.964131 | I39: -118.27278 | J39: 4 | K39: 59 | L39: Offer B | M39: Yes | N39: 16.39 | O39: Yes | P39: Yes | Q39: Fiber Optic | R39: 14.0 | S39: Yes | T39: Yes | U39: No | V39: No | W39: Yes | X39: No | Y39: No | Z39: Yes | AA39: Month-to-Month | AB39: Yes | AC39: Bank Withdrawal | AD39: 94.75 | AE39: 5597.65 | AF39: 0 | AG39: 0 | AH39: 967.01 | AI39: 6564.66 | AJ39: Stayed | AM39: 0 | AN39: 1 | AO39: 0 | AP39: 49-72 months | AQ39: 60-69 | AR39: $90+ | AS39: 4 | AT39: 58198 | AU39: 1 | AV39: 0 | AW39: 1 | AX39: 0 | AY39: 6 | AZ39: 06 | 49-72 months | BA39: 6 | BB39: Very High | BC39: 1
A40: 0064-SUDOG | B40: Female | C40: 48 | D40: Yes | E40: 3 | F40: Huntington Park | G40: 90255 | H40: 33.97803 | I40: -118.21714 | J40: 3 | K40: 12 | L40: None | M40: Yes | N40: 19.28 | O40: No | P40: No | Q40: N/A | R40: N/A | S40: N/A | T40: N/A | U40: N/A | V40: N/A | W40: N/A | X40: N/A | Y40: N/A | Z40: N/A | AA40: Two Year | AB40: No | AC40: Bank Withdrawal | AD40: 20.3 | AE40: 224.5 | AF40: 0 | AG40: 0 | AH40: 231.36 | AI40: 455.86 | AJ40: Stayed | AM40: 0 | AN40: 1 | AO40: 0 | AP40: 7-12 months | AQ40: 40-49 | AR40: Low (<$30) | AT40: 78114 | AU40: 1 | AV40: 0 | AW40: 1 | AX40: 0 | AY40: 2 | AZ40: 02 | 7-12 months | BA40: 0 | BB40: Low | BC40: 4
A41: 0064-YIJGF | B41: Male | C41: 60 | D41: Yes | E41: 3 | F41: Yermo | G41: 92398 | H41: 35.013299 | I41: -116.83409 | J41: 7 | K41: 27 | L41: Offer C | M41: Yes | N41: 25.26 | O41: Yes | P41: Yes | Q41: Fiber Optic | R41: 23.0 | S41: No | T41: No | U41: No | V41: No | W41: No | X41: No | Y41: No | Z41: Yes | AA41: Month-to-Month | AB41: Yes | AC41: Bank Withdrawal | AD41: 75.75 | AE41: 1929 | AF41: 0 | AG41: 0 | AH41: 682.02 | AI41: 2611.02 | AJ41: Stayed | AM41: 0 | AN41: 1 | AO41: 0 | AP41: 25-36 months | AQ41: 60-69 | AR41: $70-89 | AS41: 1 | AT41: 1195 | AU41: 1 | AV41: 0 | AW41: 1 | AX41: 0 | AY41: 4 | AZ41: 04 | 25-36 months | BA41: 5 | BB41: High | BC41: 2
A42: 0067-DKWBL | B42: Male | C42: 69 | D42: No | E42: 0 | F42: San Diego | G42: 92129 | H42: 32.961064 | I42: -117.13492 | J42: 0 | K42: 2 | L42: None | M42: Yes | N42: 43.99 | O42: No | P42: Yes | Q42: DSL | R42: 27.0 | S42: Yes | T42: No | U42: No | V42: No | W42: No | X42: No | Y42: No | Z42: Yes | AA42: Month-to-Month | AB42: Yes | AC42: Bank Withdrawal | AD42: 49.25 | AE42: 91.1 | AF42: 0 | AG42: 0 | AH42: 87.98 | AI42: 179.08 | AJ42: Churned | AK42: Competitor | AL42: Competitor made better offer | AM42: 1 | AN42: 0 | AO42: 0 | AP42: 0-6 months | AQ42: 60-69 | AR42: $30-49 | AS42: 2 | AT42: 47224 | AU42: 1 | AV42: 1 | AW42: 0 | AX42: 49.25 | AY42: 1 | AZ42: 01 | 0-6 months | BA42: 8 | BB42: Very High | BC42: 1
A43: 0068-FIGTF | B43: Female | C43: 20 | D43: No | E43: 0 | F43: Fremont | G43: 94539 | H43: 37.516791 | I43: -121.89912 | J43: 0 | K43: 27 | L43: Offer C | M43: Yes | N43: 48.91 | O43: No | P43: Yes | Q43: DSL | R43: 59.0 | S43: No | T43: Yes | U43: Yes | V43: Yes | W43: Yes | X43: Yes | Y43: Yes | Z43: Yes | AA43: One Year | AB43: No | AC43: Credit Card | AD43: 78.2 | AE43: 2078.95 | AF43: 0 | AG43: 0 | AH43: 1320.57 | AI43: 3399.52 | AJ43: Stayed | AM43: 0 | AN43: 1 | AO43: 0 | AP43: 25-36 months | AQ43: Under 30 | AR43: $70-89 | AS43: 7 | AT43: 46917 | AU43: 1 | AV43: 0 | AW43: 1 | AX43: 0 | AY43: 4 | AZ43: 04 | 25-36 months | BA43: 2 | BB43: Medium | BC43: 3
A44: 0071-NDAFP | B44: Male | C44: 31 | D44: Yes | E44: 3 | F44: Santa Rosa | G44: 95405 | H44: 38.439696 | I44: -122.66882 | J44: 1 | K44: 25 | L44: None | M44: Yes | N44: 23.69 | O44: Yes | P44: No | Q44: N/A | R44: N/A | S44: N/A | T44: N/A | U44: N/A | V44: N/A | W44: N/A | X44: N/A | Y44: N/A | Z44: N/A | AA44: Two Year | AB44: No | AC44: Credit Card | AD44: 25.5 | AE44: 630.6 | AF44: 44.42 | AG44: 0 | AH44: 592.25 | AI44: 1178.43 | AJ44: Stayed | AM44: 0 | AN44: 1 | AO44: 0 | AP44: 25-36 months | AQ44: 30-39 | AR44: Low (<$30) | AT44: 22250 | AU44: 1 | AV44: 0 | AW44: 1 | AX44: 0 | AY44: 4 | AZ44: 04 | 25-36 months | BA44: 0 | BB44: Low | BC44: 4
A45: 0074-HDKDG | B45: Male | C45: 46 | D45: Yes | E45: 0 | F45: San Jose | G45: 95126 | H45: 37.327069 | I45: -121.91682 | J45: 5 | K45: 25 | L45: None | M45: Yes | N45: 6.45 | O45: No | P45: Yes | Q45: Cable | R45: 19.0 | S45: Yes | T45: Yes | U45: Yes | V45: No | W45: No | X45: No | Y45: No | Z45: Yes | AA45: One Year | AB45: Yes | AC45: Bank Withdrawal | AD45: 61.6 | AE45: 1611 | AF45: 44.9 | AG45: 0 | AH45: 161.25 | AI45: 1727.35 | AJ45: Stayed | AM45: 0 | AN45: 1 | AO45: 0 | AP45: 25-36 months | AQ45: 40-49 | AR45: $50-69 | AS45: 4 | AT45: 27023 | AU45: 1 | AV45: 0 | AW45: 1 | AX45: 0 | AY45: 4 | AZ45: 04 | 25-36 months | BA45: 1 | BB45: Low | BC45: 4
A46: 0076-LVEPS | B46: Male | C46: 57 | D46: No | E46: 1 | F46: Tujunga | G46: 91042 | H46: 34.296574 | I46: -118.24484 | J46: 0 | K46: 29 | L46: None | M46: No | N46: N/A | O46: N/A | P46: Yes | Q46: DSL | R46: 21.0 | S46: Yes | T46: Yes | U46: Yes | V46: Yes | W46: No | X46: No | Y46: No | Z46: Yes | AA46: Month-to-Month | AB46: Yes | AC46: Credit Card | AD46: 45 | AE46: 1242.45 | AF46: 12.26 | AG46: 0 | AH46: 0 | AI46: 1230.19 | AJ46: Stayed | AM46: 0 | AN46: 1 | AO46: 0 | AP46: 25-36 months | AQ46: 50-59 | AR46: $30-49 | AS46: 5 | AT46: 26753 | AU46: 1 | AV46: 0 | AW46: 1 | AX46: 0 | AY46: 4 | AZ46: 04 | 25-36 months | BA46: 4 | BB46: High | BC46: 2
A47: 0078-XZMHT | B47: Male | C47: 19 | D47: Yes | E47: 0 | F47: Visalia | G47: 93291 | H47: 36.391777 | I47: -119.37284 | J47: 5 | K47: 72 | L47: None | M47: Yes | N47: 32.36 | O47: Yes | P47: Yes | Q47: DSL | R47: 52.0 | S47: No | T47: Yes | U47: Yes | V47: Yes | W47: Yes | X47: Yes | Y47: Yes | Z47: Yes | AA47: Two Year | AB47: Yes | AC47: Bank Withdrawal | AD47: 85.15 | AE47: 6316.2 | AF47: 0 | AG47: 0 | AH47: 2329.92 | AI47: 8646.12 | AJ47: Stayed | AM47: 0 | AN47: 1 | AO47: 0 | AP47: 49-72 months | AQ47: Under 30 | AR47: $70-89 | AS47: 7 | AT47: 36718 | AU47: 1 | AV47: 0 | AW47: 1 | AX47: 0 | AY47: 6 | AZ47: 06 | 49-72 months | BA47: 1 | BB47: Low | BC47: 4
A48: 0080-EMYVY | B48: Female | C48: 64 | D48: No | E48: 0 | F48: Lodi | G48: 95240 | H48: 38.123544 | I48: -121.15908 | J48: 0 | K48: 14 | L48: None | M48: Yes | N48: 24.04 | O48: No | P48: Yes | Q48: Cable | R48: 12.0 | S48: No | T48: Yes | U48: No | V48: No | W48: No | X48: No | Y48: No | Z48: Yes | AA48: One Year | AB48: No | AC48: Credit Card | AD48: 51.45 | AE48: 727.85 | AF48: 0 | AG48: 0 | AH48: 336.56 | AI48: 1064.41 | AJ48: Stayed | AM48: 0 | AN48: 1 | AO48: 0 | AP48: 13-24 months | AQ48: 60-69 | AR48: $50-69 | AS48: 2 | AT48: 45755 | AU48: 1 | AV48: 0 | AW48: 1 | AX48: 0 | AY48: 3 | AZ48: 03 | 13-24 months | BA48: 2 | BB48: Medium | BC48: 3
A49: 0080-OROZO | B49: Female | C49: 38 | D49: No | E49: 0 | F49: El Portal | G49: 95318 | H49: 37.654551 | I49: -119.82298 | J49: 0 | K49: 35 | L49: Offer C | M49: Yes | N49: 36.42 | O49: No | P49: Yes | Q49: Fiber Optic | R49: 2.0 | S49: No | T49: No | U49: Yes | V49: Yes | W49: Yes | X49: Yes | Y49: Yes | Z49: Yes | AA49: One Year | AB49: Yes | AC49: Bank Withdrawal | AD49: 99.25 | AE49: 3532 | AF49: 0 | AG49: 0 | AH49: 1274.7 | AI49: 4806.7 | AJ49: Stayed | AM49: 0 | AN49: 1 | AO49: 0 | AP49: 25-36 months | AQ49: 30-39 | AR49: $90+ | AS49: 6 | AT49: 579 | AU49: 1 | AV49: 0 | AW49: 1 | AX49: 0 | AY49: 4 | AZ49: 04 | 25-36 months | BA49: 4 | BB49: High | BC49: 2
A50: 0082-LDZUE | B50: Male | C50: 54 | D50: No | E50: 0 | F50: Calistoga | G50: 94515 | H50: 38.629618 | I50: -122.59322 | J50: 0 | K50: 1 | L50: Offer E | M50: Yes | N50: 42.95 | O50: No | P50: Yes | Q50: DSL | R50: 9.0 | S50: No | T50: No | U50: No | V50: No | W50: No | X50: No | Y50: No | Z50: Yes | AA50: Month-to-Month | AB50: Yes | AC50: Credit Card | AD50: 44.3 | AE50: 44.3 | AF50: 0 | AG50: 0 | AH50: 42.95 | AI50: 87.25 | AJ50: Joined | AM50: 0 | AN50: 0 | AO50: 0 | AP50: 0-6 months | AQ50: 50-59 | AR50: $30-49 | AS50: 1 | AT50: 7384 | AU50: 0 | AX50: 0 | AY50: 1 | AZ50: 01 | 0-6 months | BA50: 8 | BB50: Very High | BC50: 1
A51: 0082-OQIQY | B51: Male | C51: 50 | D51: No | E51: 0 | F51: Farmington | G51: 95230 | H51: 37.956963 | I51: -120.86306 | J51: 0 | K51: 29 | L51: None | M51: Yes | N51: 2.05 | O51: No | P51: Yes | Q51: Fiber Optic | R51: 17.0 | S51: No | T51: No | U51: No | V51: Yes | W51: Yes | X51: Yes | Y51: Yes | Z51: No | AA51: Month-to-Month | AB51: Yes | AC51: Bank Withdrawal | AD51: 94.2 | AE51: 2607.6 | AF51: 0 | AG51: 20 | AH51: 59.45 | AI51: 2687.05 | AJ51: Stayed | AM51: 0 | AN51: 1 | AO51: 0 | AP51: 25-36 months | AQ51: 50-59 | AR51: $90+ | AS51: 4 | AT51: 596 | AU51: 1 | AV51: 0 | AW51: 1 | AX51: 0 | AY51: 4 | AZ51: 04 | 25-36 months | BA51: 7 | BB51: Very High | BC51: 1
A52: 0083-PIVIK | B52: Male | C52: 25 | D52: No | E52: 0 | F52: Tulelake | G52: 96134 | H52: 41.813521 | I52: -121.49267 | J52: 0 | K52: 64 | L52: None | M52: Yes | N52: 5.49 | O52: Yes | P52: Yes | Q52: DSL | R52: 69.0 | S52: Yes | T52: Yes | U52: Yes | V52: Yes | W52: Yes | X52: No | Y52: No | Z52: No | AA52: One Year | AB52: No | AC52: Bank Withdrawal | AD52: 81.25 | AE52: 5567.55 | AF52: 0 | AG52: 40 | AH52: 351.36 | AI52: 5958.91 | AJ52: Stayed | AM52: 0 | AN52: 1 | AO52: 0 | AP52: 49-72 months | AQ52: Under 30 | AR52: $70-89 | AS52: 5 | AT52: 2595 | AU52: 1 | AV52: 0 | AW52: 1 | AX52: 0 | AY52: 6 | AZ52: 06 | 49-72 months | BA52: 2 | BB52: Medium | BC52: 3
A53: 0089-IIQKO | B53: Female | C53: 35 | D53: Yes | E53: 3 | F53: Coleville | G53: 96107 | H53: 38.42528 | I53: -119.47574 | J53: 1 | K53: 39 | L53: None | M53: Yes | N53: 24.38 | O53: Yes | P53: Yes | Q53: Fiber Optic | R53: 53.0 | S53: No | T53: No | U53: No | V53: Yes | W53: Yes | X53: Yes | Y53: Yes | Z53: Yes | AA53: Month-to-Month | AB53: Yes | AC53: Credit Card | AD53: 99.95 | AE53: 3767.4 | AF53: 0 | AG53: 0 | AH53: 950.82 | AI53: 4718.22 | AJ53: Stayed | AM53: 0 | AN53: 1 | AO53: 0 | AP53: 37-48 months | AQ53: 30-39 | AR53: $90+ | AS53: 5 | AT53: 1332 | AU53: 1 | AV53: 0 | AW53: 1 | AX53: 0 | AY53: 5 | AZ53: 05 | 37-48 months | BA53: 5 | BB53: High | BC53: 2
A54: 0093-EXYQL | B54: Female | C54: 72 | D54: No | E54: 0 | F54: Ojai | G54: 93023 | H54: 34.581308 | I54: -118.93195 | J54: 0 | K54: 40 | L54: None | M54: Yes | N54: 44.14 | O54: No | P54: Yes | Q54: Fiber Optic | R54: 23.0 | S54: No | T54: No | U54: No | V54: No | W54: Yes | X54: Yes | Y54: No | Z54: Yes | AA54: Two Year | AB54: Yes | AC54: Bank Withdrawal | AD54: 91.55 | AE54: 3673.6 | AF54: 0 | AG54: 0 | AH54: 1765.6 | AI54: 5439.2 | AJ54: Stayed | AM54: 0 | AN54: 1 | AO54: 0 | AP54: 37-48 months | AQ54: 70+ | AR54: $90+ | AS54: 3 | AT54: 21633 | AU54: 1 | AV54: 0 | AW54: 1 | AX54: 0 | AY54: 5 | AZ54: 05 | 37-48 months | BA54: 4 | BB54: High | BC54: 2
A55: 0093-XWZFY | B55: Male | C55: 51 | D55: No | E55: 0 | F55: Desert Hot Springs | G55: 92241 | H55: 33.832799 | I55: -116.25097 | J55: 0 | K55: 40 | L55: None | M55: Yes | N55: 37.69 | O55: Yes | P55: Yes | Q55: Fiber Optic | R55: 15.0 | S55: No | T55: Yes | U55: Yes | V55: No | W55: Yes | X55: Yes | Y55: Yes | Z55: Yes | AA55: Month-to-Month | AB55: Yes | AC55: Credit Card | AD55: 104.5 | AE55: 4036.85 | AF55: 0 | AG55: 0 | AH55: 1507.6 | AI55: 5544.45 | AJ55: Churned | AK55: Competitor | AL55: Competitor had better devices | AM55: 1 | AN55: 0 | AO55: 0 | AP55: 37-48 months | AQ55: 50-59 | AR55: $90+ | AS55: 6 | AT55: 5529 | AU55: 1 | AV55: 1 | AW55: 0 | AX55: 104.5 | AY55: 5 | AZ55: 05 | 37-48 months | BA55: 7 | BB55: Very High | BC55: 1
A56: 0094-OIFMO | B56: Female | C56: 78 | D56: No | E56: 1 | F56: North Hollywood | G56: 91605 | H56: 34.207295 | I56: -118.40002 | J56: 0 | K56: 11 | L56: Offer D | M56: Yes | N56: 11.59 | O56: No | P56: Yes | Q56: Fiber Optic | R56: 29.0 | S56: No | T56: Yes | U56: No | V56: No | W56: Yes | X56: Yes | Y56: No | Z56: No | AA56: Month-to-Month | AB56: Yes | AC56: Bank Withdrawal | AD56: 95 | AE56: 1120.3 | AF56: 0 | AG56: 120 | AH56: 127.49 | AI56: 1367.79 | AJ56: Churned | AK56: Dissatisfaction | AL56: Product dissatisfaction | AM56: 1 | AN56: 0 | AO56: 0 | AP56: 7-12 months | AQ56: 70+ | AR56: $90+ | AS56: 3 | AT56: 57146 | AU56: 1 | AV56: 1 | AW56: 0 | AX56: 95 | AY56: 2 | AZ56: 02 | 7-12 months | BA56: 6 | BB56: Very High | BC56: 1
A57: 0096-BXERS | B57: Female | C57: 30 | D57: Yes | E57: 0 | F57: Inverness | G57: 94937 | H57: 38.099323 | I57: -122.94572 | J57: 10 | K57: 6 | L57: Offer E | M57: Yes | N57: 42.66 | O57: Yes | P57: Yes | Q57: Cable | R57: 85.0 | S57: No | T57: No | U57: No | V57: No | W57: No | X57: No | Y57: No | Z57: Yes | AA57: Month-to-Month | AB57: No | AC57: Bank Withdrawal | AD57: 50.35 | AE57: 314.55 | AF57: 0 | AG57: 0 | AH57: 255.96 | AI57: 570.51 | AJ57: Stayed | AM57: 0 | AN57: 1 | AO57: 0 | AP57: 0-6 months | AQ57: 30-39 | AR57: $50-69 | AS57: 1 | AT57: 1004 | AU57: 1 | AV57: 0 | AW57: 1 | AX57: 0 | AY57: 1 | AZ57: 01 | 0-6 months | BA57: 7 | BB57: Very High | BC57: 1
A58: 0096-FCPUF | B58: Male | C58: 58 | D58: No | E58: 0 | F58: Santa Rosa | G58: 95404 | H58: 38.526941 | I58: -122.7091 | J58: 0 | K58: 30 | L58: None | M58: Yes | N58: 2.64 | O58: Yes | P58: Yes | Q58: DSL | R58: 15.0 | S58: Yes | T58: No | U58: No | V58: No | W58: No | X58: Yes | Y58: Yes | Z58: Yes | AA58: Month-to-Month | AB58: Yes | AC58: Mailed Check | AD58: 64.5 | AE58: 1888.45 | AF58: 0 | AG58: 0 | AH58: 79.2 | AI58: 1967.65 | AJ58: Stayed | AM58: 0 | AN58: 1 | AO58: 0 | AP58: 25-36 months | AQ58: 50-59 | AR58: $50-69 | AS58: 4 | AT58: 35057 | AU58: 1 | AV58: 0 | AW58: 1 | AX58: 0 | AY58: 4 | AZ58: 04 | 25-36 months | BA58: 5 | BB58: High | BC58: 2
A59: 0098-BOWSO | B59: Male | C59: 26 | D59: No | E59: 0 | F59: San Jose | G59: 95131 | H59: 37.387027 | I59: -121.89777 | J59: 0 | K59: 27 | L59: None | M59: Yes | N59: 20.66 | O59: No | P59: No | Q59: N/A | R59: N/A | S59: N/A | T59: N/A | U59: N/A | V59: N/A | W59: N/A | X59: N/A | Y59: N/A | Z59: N/A | AA59: Month-to-Month | AB59: Yes | AC59: Bank Withdrawal | AD59: 19.4 | AE59: 529.8 | AF59: 0 | AG59: 0 | AH59: 557.82 | AI59: 1087.62 | AJ59: Stayed | AM59: 0 | AN59: 1 | AO59: 0 | AP59: 25-36 months | AQ59: Under 30 | AR59: Low (<$30) | AT59: 26389 | AU59: 1 | AV59: 0 | AW59: 1 | AX59: 0 | AY59: 4 | AZ59: 04 | 25-36 months | BA59: 5 | BB59: High | BC59: 2
A60: 0100-DUVFC | B60: Male | C60: 66 | D60: Yes | E60: 0 | F60: Wilmington | G60: 90744 | H60: 33.782068 | I60: -118.26226 | J60: 3 | K60: 70 | L60: None | M60: Yes | N60: 39.49 | O60: Yes | P60: Yes | Q60: Fiber Optic | R60: 28.0 | S60: No | T60: Yes | U60: Yes | V60: No | W60: Yes | X60: Yes | Y60: No | Z60: Yes | AA60: One Year | AB60: Yes | AC60: Bank Withdrawal | AD60: 104.8 | AE60: 7308.95 | AF60: 6.11 | AG60: 0 | AH60: 2764.3 | AI60: 10067.14 | AJ60: Stayed | AM60: 0 | AN60: 1 | AO60: 0 | AP60: 49-72 months | AQ60: 60-69 | AR60: $90+ | AS60: 5 | AT60: 53323 | AU60: 1 | AV60: 0 | AW60: 1 | AX60: 0 | AY60: 6 | AZ60: 06 | 49-72 months | BA60: 3 | BB60: Medium | BC60: 3
A61: 0103-CSITQ | B61: Female | C61: 20 | D61: Yes | E61: 0 | F61: Modesto | G61: 95357 | H61: 37.670526 | I61: -120.87757 | J61: 10 | K61: 57 | L61: Offer B | M61: Yes | N61: 8.01 | O61: Yes | P61: Yes | Q61: Fiber Optic | R61: 73.0 | S61: No | T61: Yes | U61: Yes | V61: Yes | W61: Yes | X61: Yes | Y61: Yes | Z61: Yes | AA61: One Year | AB61: Yes | AC61: Bank Withdrawal | AD61: 109.4 | AE61: 6252.7 | AF61: 0 | AG61: 0 | AH61: 456.57 | AI61: 6709.27 | AJ61: Stayed | AM61: 0 | AN61: 1 | AO61: 0 | AP61: 49-72 months | AQ61: Under 30 | AR61: $90+ | AS61: 7 | AT61: 13343 | AU61: 1 | AV61: 0 | AW61: 1 | AX61: 0 | AY61: 6 | AZ61: 06 | 49-72 months | BA61: 3 | BB61: Medium | BC61: 3
A62: 0104-PPXDV | B62: Male | C62: 61 | D62: Yes | E62: 0 | F62: San Diego | G62: 92113 | H62: 32.697098 | I62: -117.11659 | J62: 10 | K62: 58 | L62: None | M62: Yes | N62: 18.37 | O62: No | P62: Yes | Q62: DSL | R62: 18.0 | S62: No | T62: No | U62: Yes | V62: No | W62: No | X62: No | Y62: No | Z62: Yes | AA62: One Year | AB62: No | AC62: Credit Card | AD62: 50.3 | AE62: 2878.55 | AF62: 10.23 | AG62: 0 | AH62: 1065.46 | AI62: 3933.78 | AJ62: Stayed | AM62: 0 | AN62: 1 | AO62: 0 | AP62: 49-72 months | AQ62: 60-69 | AR62: $50-69 | AS62: 2 | AT62: 47431 | AU62: 1 | AV62: 0 | AW62: 1 | AX62: 0 | AY62: 6 | AZ62: 06 | 49-72 months | BA62: 1 | BB62: Low | BC62: 4
A63: 0106-GHRQR | B63: Male | C63: 24 | D63: No | E63: 0 | F63: Rancho Palos Verdes | G63: 90275 | H63: 33.753146 | I63: -118.36746 | J63: 0 | K63: 16 | L63: None | M63: Yes | N63: 25.71 | O63: Yes | P63: Yes | Q63: DSL | R63: 48.0 | S63: No | T63: Yes | U63: Yes | V63: No | W63: No | X63: Yes | Y63: Yes | Z63: Yes | AA63: Month-to-Month | AB63: Yes | AC63: Bank Withdrawal | AD63: 71.4 | AE63: 1212.1 | AF63: 0 | AG63: 0 | AH63: 411.36 | AI63: 1623.46 | AJ63: Stayed | AM63: 0 | AN63: 1 | AO63: 0 | AP63: 13-24 months | AQ63: Under 30 | AR63: $70-89 | AS63: 5 | AT63: 41263 | AU63: 1 | AV63: 0 | AW63: 1 | AX63: 0 | AY63: 3 | AZ63: 03 | 13-24 months | BA63: 5 | BB63: High | BC63: 2
A64: 0106-UGRDO | B64: Female | C64: 55 | D64: Yes | E64: 0 | F64: Kenwood | G64: 95452 | H64: 38.419525 | I64: -122.52159 | J64: 3 | K64: 69 | L64: Offer A | M64: Yes | N64: 38.52 | O64: Yes | P64: Yes | Q64: Fiber Optic | R64: 27.0 | S64: Yes | T64: Yes | U64: Yes | V64: Yes | W64: Yes | X64: Yes | Y64: Yes | Z64: Yes | AA64: Two Year | AB64: Yes | AC64: Bank Withdrawal | AD64: 116 | AE64: 8182.85 | AF64: 0 | AG64: 0 | AH64: 2657.88 | AI64: 10840.73 | AJ64: Stayed | AM64: 0 | AN64: 1 | AO64: 0 | AP64: 49-72 months | AQ64: 50-59 | AR64: $90+ | AS64: 8 | AT64: 1653 | AU64: 1 | AV64: 0 | AW64: 1 | AX64: 0 | AY64: 6 | AZ64: 06 | 49-72 months | BA64: 3 | BB64: Medium | BC64: 3
A65: 0107-WESLM | B65: Male | C65: 32 | D65: No | E65: 0 | F65: West Point | G65: 95255 | H65: 38.41935 | I65: -120.46954 | J65: 0 | K65: 1 | L65: Offer E | M65: Yes | N65: 31.77 | O65: No | P65: No | Q65: N/A | R65: N/A | S65: N/A | T65: N/A | U65: N/A | V65: N/A | W65: N/A | X65: N/A | Y65: N/A | Z65: N/A | AA65: Month-to-Month | AB65: Yes | AC65: Bank Withdrawal | AD65: 19.85 | AE65: 19.85 | AF65: 0 | AG65: 0 | AH65: 31.77 | AI65: 51.62 | AJ65: Churned | AK65: Attitude | AL65: Attitude of support person | AM65: 1 | AN65: 0 | AO65: 0 | AP65: 0-6 months | AQ65: 30-39 | AR65: Low (<$30) | AT65: 2198 | AU65: 1 | AV65: 1 | AW65: 0 | AX65: 19.85 | AY65: 1 | AZ65: 01 | 0-6 months | BA65: 8 | BB65: Very High | BC65: 1
A66: 0107-YHINA | B66: Male | C66: 59 | D66: No | E66: 0 | F66: Los Angeles | G66: 90062 | H66: 34.003553 | I66: -118.30893 | J66: 0 | K66: 1 | L66: None | M66: Yes | N66: 40.71 | O66: Yes | P66: Yes | Q66: Fiber Optic | R66: 25.0 | S66: No | T66: No | U66: Yes | V66: No | W66: Yes | X66: Yes | Y66: Yes | Z66: Yes | AA66: Month-to-Month | AB66: Yes | AC66: Bank Withdrawal | AD66: 99.75 | AE66: 99.75 | AF66: 0 | AG66: 0 | AH66: 40.71 | AI66: 140.46 | AJ66: Churned | AK66: Competitor | AL66: Competitor had better devices | AM66: 1 | AN66: 0 | AO66: 0 | AP66: 0-6 months | AQ66: 50-59 | AR66: $90+ | AS66: 5 | AT66: 29299 | AU66: 1 | AV66: 1 | AW66: 0 | AX66: 99.75 | AY66: 1 | AZ66: 01 | 0-6 months | BA66: 10 | BB66: Very High | BC66: 1
A67: 0111-KLBQG | B67: Male | C67: 71 | D67: Yes | E67: 1 | F67: Morongo Valley | G67: 92256 | H67: 34.097863 | I67: -116.59456 | J67: 9 | K67: 32 | L67: Offer C | M67: Yes | N67: 31.86 | O67: No | P67: Yes | Q67: Fiber Optic | R67: 23.0 | S67: No | T67: Yes | U67: No | V67: No | W67: Yes | X67: Yes | Y67: Yes | Z67: Yes | AA67: One Year | AB67: Yes | AC67: Mailed Check | AD67: 93.95 | AE67: 2861.45 | AF67: 0 | AG67: 0 | AH67: 1019.52 | AI67: 3880.97 | AJ67: Stayed | AM67: 0 | AN67: 1 | AO67: 0 | AP67: 25-36 months | AQ67: 70+ | AR67: $90+ | AS67: 5 | AT67: 3499 | AU67: 1 | AV67: 0 | AW67: 1 | AX67: 0 | AY67: 4 | AZ67: 04 | 25-36 months | BA67: 2 | BB67: Medium | BC67: 3
A68: 0112-QAWRZ | B68: Male | C68: 49 | D68: Yes | E68: 2 | F68: Palo Verde | G68: 92266 | H68: 33.3249 | I68: -114.75833 | J68: 8 | K68: 16 | L68: Offer D | M68: Yes | N68: 48.71 | O68: Yes | P68: Yes | Q68: Fiber Optic | R68: 12.0 | S68: No | T68: No | U68: Yes | V68: No | W68: Yes | X68: No | Y68: No | Z68: Yes | AA68: Month-to-Month | AB68: Yes | AC68: Bank Withdrawal | AD68: 90.8 | AE68: 1442.2 | AF68: 0 | AG68: 0 | AH68: 779.36 | AI68: 2221.56 | AJ68: Stayed | AM68: 0 | AN68: 1 | AO68: 0 | AP68: 13-24 months | AQ68: 40-49 | AR68: $90+ | AS68: 3 | AT68: 291 | AU68: 1 | AV68: 0 | AW68: 1 | AX68: 0 | AY68: 3 | AZ68: 03 | 13-24 months | BA68: 5 | BB68: High | BC68: 2
A69: 0112-QWPNC | B69: Male | C69: 61 | D69: Yes | E69: 0 | F69: Valyermo | G69: 93563 | H69: 34.39583 | I69: -117.73457 | J69: 1 | K69: 49 | L69: Offer B | M69: Yes | N69: 39.55 | O69: Yes | P69: Yes | Q69: Cable | R69: 10.0 | S69: Yes | T69: No | U69: Yes | V69: Yes | W69: Yes | X69: Yes | Y69: Yes | Z69: Yes | AA69: One Year | AB69: No | AC69: Bank Withdrawal | AD69: 84.35 | AE69: 4059.35 | AF69: 0 | AG69: 0 | AH69: 1937.95 | AI69: 5997.3 | AJ69: Churned | AK69: Competitor | AL69: Competitor offered higher download speeds | AM69: 1 | AN69: 0 | AO69: 0 | AP69: 49-72 months | AQ69: 60-69 | AR69: $70-89 | AS69: 7 | AT69: 413 | AU69: 1 | AV69: 1 | AW69: 0 | AX69: 84.35 | AY69: 6 | AZ69: 06 | 49-72 months | BA69: 1 | BB69: Low | BC69: 4
A70: 0114-IGABW | B70: Female | C70: 40 | D70: Yes | E70: 0 | F70: Cambria | G70: 93428 | H70: 35.591387 | I70: -121.03226 | J70: 2 | K70: 71 | L70: Offer A | M70: No | N70: N/A | O70: N/A | P70: Yes | Q70: Cable | R70: 29.0 | S70: No | T70: Yes | U70: Yes | V70: Yes | W70: Yes | X70: Yes | Y70: Yes | Z70: Yes | AA70: Two Year | AB70: No | AC70: Bank Withdrawal | AD70: 58.25 | AE70: 4145.9 | AF70: 0 | AG70: 0 | AH70: 0 | AI70: 4145.9 | AJ70: Stayed | AM70: 0 | AN70: 1 | AO70: 0 | AP70: 49-72 months | AQ70: 40-49 | AR70: $50-69 | AS70: 7 | AT70: 6526 | AU70: 1 | AV70: 0 | AW70: 1 | AX70: 0 | AY70: 6 | AZ70: 06 | 49-72 months | BA70: 1 | BB70: Low | BC70: 4
A71: 0114-PEGZZ | B71: Female | C71: 39 | D71: No | E71: 0 | F71: Round Mountain | G71: 96084 | H71: 40.923558 | I71: -122.05993 | J71: 0 | K71: 33 | L71: None | M71: Yes | N71: 49.69 | O71: Yes | P71: Yes | Q71: Fiber Optic | R71: 12.0 | S71: No | T71: Yes | U71: Yes | V71: No | W71: Yes | X71: Yes | Y71: Yes | Z71: Yes | AA71: Month-to-Month | AB71: No | AC71: Bank Withdrawal | AD71: 107.55 | AE71: 3645.5 | AF71: 0 | AG71: 0 | AH71: 1639.77 | AI71: 5285.27 | AJ71: Stayed | AM71: 0 | AN71: 1 | AO71: 0 | AP71: 25-36 months | AQ71: 30-39 | AR71: $90+ | AS71: 6 | AT71: 459 | AU71: 1 | AV71: 0 | AW71: 1 | AX71: 0 | AY71: 4 | AZ71: 04 | 25-36 months | BA71: 7 | BB71: Very High | BC71: 1
A72: 0114-RSRRW | B72: Female | C72: 21 | D72: Yes | E72: 0 | F72: Klamath | G72: 95548 | H72: 41.572813 | I72: -124.03501 | J72: 9 | K72: 10 | L72: Offer D | M72: Yes | N72: 49.6 | O72: No | P72: No | Q72: N/A | R72: N/A | S72: N/A | T72: N/A | U72: N/A | V72: N/A | W72: N/A | X72: N/A | Y72: N/A | Z72: N/A | AA72: Month-to-Month | AB72: Yes | AC72: Bank Withdrawal | AD72: 19.95 | AE72: 187.75 | AF72: 0 | AG72: 0 | AH72: 496 | AI72: 683.75 | AJ72: Stayed | AM72: 0 | AN72: 1 | AO72: 0 | AP72: 7-12 months | AQ72: Under 30 | AR72: Low (<$30) | AT72: 1215 | AU72: 1 | AV72: 0 | AW72: 1 | AX72: 0 | AY72: 2 | AZ72: 02 | 7-12 months | BA72: 4 | BB72: High | BC72: 2
A73: 0115-TFERT | B73: Male | C73: 24 | D73: Yes | E73: 0 | F73: Fresno | G73: 93650 | H73: 36.841655 | I73: -119.79711 | J73: 1 | K73: 21 | L73: None | M73: Yes | N73: 36.26 | O73: Yes | P73: Yes | Q73: Fiber Optic | R73: 59.0 | S73: No | T73: Yes | U73: Yes | V73: Yes | W73: Yes | X73: Yes | Y73: Yes | Z73: No | AA73: Month-to-Month | AB73: Yes | AC73: Bank Withdrawal | AD73: 111.2 | AE73: 2317.1 | AF73: 0 | AG73: 120 | AH73: 761.46 | AI73: 3198.56 | AJ73: Churned | AK73: Attitude | AL73: Attitude of service provider | AM73: 1 | AN73: 0 | AO73: 0 | AP73: 13-24 months | AQ73: Under 30 | AR73: $90+ | AS73: 6 | AT73: 3258 | AU73: 1 | AV73: 1 | AW73: 0 | AX73: 111.2 | AY73: 3 | AZ73: 03 | 13-24 months | BA73: 6 | BB73: Very High | BC73: 1
A74: 0117-LFRMW | B74: Male | C74: 52 | D74: Yes | E74: 1 | F74: Angwin | G74: 94508 | H74: 38.542448 | I74: -122.41992 | J74: 1 | K74: 37 | L74: None | M74: No | N74: N/A | O74: N/A | P74: Yes | Q74: DSL | R74: 23.0 | S74: Yes | T74: Yes | U74: Yes | V74: No | W74: No | X74: No | Y74: No | Z74: Yes | AA74: Month-to-Month | AB74: No | AC74: Bank Withdrawal | AD74: 40.2 | AE74: 1448.8 | AF74: 0 | AG74: 0 | AH74: 0 | AI74: 1448.8 | AJ74: Churned | AK74: Competitor | AL74: Competitor offered more data | AM74: 1 | AN74: 0 | AO74: 0 | AP74: 37-48 months | AQ74: 50-59 | AR74: $30-49 | AS74: 4 | AT74: 3641 | AU74: 1 | AV74: 1 | AW74: 0 | AX74: 40.2 | AY74: 5 | AZ74: 05 | 37-48 months | BA74: 3 | BB74: Medium | BC74: 3
A75: 0118-JPNOY | B75: Female | C75: 71 | D75: No | E75: 0 | F75: Le Grand | G75: 95333 | H75: 37.249377 | I75: -120.24958 | J75: 0 | K75: 26 | L75: None | M75: Yes | N75: 33.74 | O75: No | P75: Yes | Q75: Fiber Optic | R75: 7.0 | S75: Yes | T75: No | U75: No | V75: No | W75: Yes | X75: No | Y75: No | Z75: Yes | AA75: Month-to-Month | AB75: Yes | AC75: Credit Card | AD75: 85.8 | AE75: 2193.65 | AF75: 0 | AG75: 0 | AH75: 877.24 | AI75: 3070.89 | AJ75: Stayed | AM75: 0 | AN75: 1 | AO75: 0 | AP75: 25-36 months | AQ75: 70+ | AR75: $70-89 | AS75: 3 | AT75: 3256 | AU75: 1 | AV75: 0 | AW75: 1 | AX75: 0 | AY75: 4 | AZ75: 04 | 25-36 months | BA75: 7 | BB75: Very High | BC75: 1
A76: 0121-SNYRK | B76: Male | C76: 45 | D76: No | E76: 0 | F76: Redway | G76: 95560 | H76: 40.142256 | I76: -123.85293 | J76: 0 | K76: 50 | L76: Offer B | M76: No | N76: N/A | O76: N/A | P76: Yes | Q76: DSL | R76: 7.0 | S76: Yes | T76: No | U76: No | V76: Yes | W76: No | X76: No | Y76: No | Z76: Yes | AA76: One Year | AB76: Yes | AC76: Credit Card | AD76: 35.4 | AE76: 1748.9 | AF76: 0 | AG76: 0 | AH76: 0 | AI76: 1748.9 | AJ76: Stayed | AM76: 0 | AN76: 1 | AO76: 0 | AP76: 49-72 months | AQ76: 40-49 | AR76: $30-49 | AS76: 3 | AT76: 1851 | AU76: 1 | AV76: 0 | AW76: 1 | AX76: 0 | AY76: 6 | AZ76: 06 | 49-72 months | BA76: 2 | BB76: Medium | BC76: 3
A77: 0122-OAHPZ | B77: Female | C77: 29 | D77: No | E77: 0 | F77: San Diego | G77: 92122 | H77: 32.85723 | I77: -117.20977 | J77: 0 | K77: 7 | L77: None | M77: Yes | N77: 28.62 | O77: Yes | P77: Yes | Q77: Fiber Optic | R77: 26.0 | S77: No | T77: No | U77: No | V77: No | W77: No | X77: No | Y77: Yes | Z77: Yes | AA77: Month-to-Month | AB77: Yes | AC77: Bank Withdrawal | AD77: 73.85 | AE77: 511.25 | AF77: 13.03 | AG77: 0 | AH77: 200.34 | AI77: 698.56 | AJ77: Churned | AK77: Competitor | AL77: Competitor made better offer | AM77: 1 | AN77: 0 | AO77: 0 | AP77: 7-12 months | AQ77: Under 30 | AR77: $70-89 | AS77: 2 | AT77: 34902 | AU77: 1 | AV77: 1 | AW77: 0 | AX77: 73.85 | AY77: 2 | AZ77: 02 | 7-12 months | BA77: 7 | BB77: Very High | BC77: 1
A78: 0123-CRBRT | B78: Female | C78: 62 | D78: Yes | E78: 0 | F78: Monterey Park | G78: 91755 | H78: 34.049172 | I78: -118.11502 | J78: 1 | K78: 61 | L78: Offer B | M78: Yes | N78: 47.19 | O78: Yes | P78: Yes | Q78: DSL | R78: 28.0 | S78: Yes | T78: Yes | U78: Yes | V78: Yes | W78: Yes | X78: Yes | Y78: Yes | Z78: Yes | AA78: Two Year | AB78: No | AC78: Mailed Check | AD78: 88.1 | AE78: 5526.75 | AF78: 0 | AG78: 0 | AH78: 2878.59 | AI78: 8405.34 | AJ78: Stayed | AM78: 0 | AN78: 1 | AO78: 0 | AP78: 49-72 months | AQ78: 60-69 | AR78: $70-89 | AS78: 8 | AT78: 26933 | AU78: 1 | AV78: 0 | AW78: 1 | AX78: 0 | AY78: 6 | AZ78: 06 | 49-72 months | BA78: 1 | BB78: Low | BC78: 4
A79: 0125-LZQXK | B79: Male | C79: 42 | D79: No | E79: 0 | F79: Big Oak Flat | G79: 95305 | H79: 37.818589 | I79: -120.257 | J79: 0 | K79: 15 | L79: Offer D | M79: Yes | N79: 45.92 | O79: No | P79: Yes | Q79: Fiber Optic | R79: 12.0 | S79: No | T79: No | U79: Yes | V79: Yes | W79: Yes | X79: Yes | Y79: Yes | Z79: Yes | AA79: Month-to-Month | AB79: Yes | AC79: Bank Withdrawal | AD79: 101.35 | AE79: 1553.95 | AF79: 0 | AG79: 0 | AH79: 688.8 | AI79: 2242.75 | AJ79: Churned | AK79: Attitude | AL79: Attitude of service provider | AM79: 1 | AN79: 0 | AO79: 0 | AP79: 13-24 months | AQ79: 40-49 | AR79: $90+ | AS79: 6 | AT79: 167 | AU79: 1 | AV79: 1 | AW79: 0 | AX79: 101.35 | AY79: 3 | AZ79: 03 | 13-24 months | BA79: 7 | BB79: Very High | BC79: 1
A80: 0128-MKWSG | B80: Female | C80: 51 | D80: No | E80: 2 | F80: Stevenson Ranch | G80: 91381 | H80: 34.364153 | I80: -118.61558 | J80: 0 | K80: 26 | L80: None | M80: No | N80: N/A | O80: N/A | P80: Yes | Q80: DSL | R80: 19.0 | S80: Yes | T80: No | U80: No | V80: Yes | W80: No | X80: Yes | Y80: Yes | Z80: Yes | AA80: Month-to-Month | AB80: No | AC80: Credit Card | AD80: 45.8 | AE80: 1147 | AF80: 0 | AG80: 0 | AH80: 0 | AI80: 1147 | AJ80: Stayed | AM80: 0 | AN80: 1 | AO80: 0 | AP80: 25-36 months | AQ80: 50-59 | AR80: $30-49 | AS80: 5 | AT80: 9937 | AU80: 1 | AV80: 0 | AW80: 1 | AX80: 0 | AY80: 4 | AZ80: 04 | 25-36 months | BA80: 4 | BB80: High | BC80: 2
A81: 0129-KPTWJ | B81: Male | C81: 39 | D81: Yes | E81: 0 | F81: North Highlands | G81: 95660 | H81: 38.671295 | I81: -121.38825 | J81: 9 | K81: 72 | L81: None | M81: Yes | N81: 33.22 | O81: No | P81: Yes | Q81: Fiber Optic | R81: 23.0 | S81: No | T81: No | U81: Yes | V81: No | W81: Yes | X81: Yes | Y81: Yes | Z81: Yes | AA81: Month-to-Month | AB81: Yes | AC81: Bank Withdrawal | AD81: 94.65 | AE81: 6747.35 | AF81: 0 | AG81: 0 | AH81: 2391.84 | AI81: 9139.19 | AJ81: Stayed | AM81: 0 | AN81: 1 | AO81: 0 | AP81: 49-72 months | AQ81: 30-39 | AR81: $90+ | AS81: 5 | AT81: 32202 | AU81: 1 | AV81: 0 | AW81: 1 | AX81: 0 | AY81: 6 | AZ81: 06 | 49-72 months | BA81: 6 | BB81: Very High | BC81: 1
A82: 0129-QMPDR | B82: Male | C82: 64 | D82: Yes | E82: 0 | F82: La Puente | G82: 91746 | H82: 34.038983 | I82: -117.99137 | J82: 1 | K82: 44 | L82: None | M82: Yes | N82: 27.4 | O82: No | P82: No | Q82: N/A | R82: N/A | S82: N/A | T82: N/A | U82: N/A | V82: N/A | W82: N/A | X82: N/A | Y82: N/A | Z82: N/A | AA82: One Year | AB82: Yes | AC82: Bank Withdrawal | AD82: 20.5 | AE82: 865.05 | AF82: 0 | AG82: 0 | AH82: 1205.6 | AI82: 2070.65 | AJ82: Stayed | AM82: 0 | AN82: 1 | AO82: 0 | AP82: 37-48 months | AQ82: 60-69 | AR82: Low (<$30) | AT82: 30802 | AU82: 1 | AV82: 0 | AW82: 1 | AX82: 0 | AY82: 5 | AZ82: 05 | 37-48 months | BA82: 1 | BB82: Low | BC82: 4
A83: 0130-SXOUN | B83: Male | C83: 55 | D83: No | E83: 0 | F83: Glenhaven | G83: 95443 | H83: 39.045246 | I83: -122.74318 | J83: 0 | K83: 66 | L83: Offer A | M83: Yes | N83: 48.78 | O83: Yes | P83: Yes | Q83: Fiber Optic | R83: 8.0 | S83: No | T83: Yes | U83: No | V83: No | W83: No | X83: Yes | Y83: Yes | Z83: No | AA83: Month-to-Month | AB83: No | AC83: Credit Card | AD83: 89.4 | AE83: 5976.9 | AF83: 36.02 | AG83: 40 | AH83: 3219.48 | AI83: 9200.36 | AJ83: Stayed | AM83: 0 | AN83: 1 | AO83: 0 | AP83: 49-72 months | AQ83: 50-59 | AR83: $70-89 | AS83: 3 | AT83: 175 | AU83: 1 | AV83: 0 | AW83: 1 | AX83: 0 | AY83: 6 | AZ83: 06 | 49-72 months | BA83: 7 | BB83: Very High | BC83: 1
A84: 0133-BMFZO | B84: Female | C84: 40 | D84: No | E84: 0 | F84: Alhambra | G84: 91803 | H84: 34.074736 | I84: -118.14596 | J84: 0 | K84: 2 | L84: None | M84: Yes | N84: 36.81 | O84: No | P84: Yes | Q84: Fiber Optic | R84: 16.0 | S84: Yes | T84: Yes | U84: No | V84: Yes | W84: No | X84: No | Y84: No | Z84: Yes | AA84: Month-to-Month | AB84: Yes | AC84: Bank Withdrawal | AD84: 86.25 | AE84: 181.65 | AF84: 0 | AG84: 0 | AH84: 73.62 | AI84: 255.27 | AJ84: Churned | AK84: Competitor | AL84: Competitor offered higher download speeds | AM84: 1 | AN84: 0 | AO84: 0 | AP84: 0-6 months | AQ84: 40-49 | AR84: $70-89 | AS84: 4 | AT84: 30635 | AU84: 1 | AV84: 1 | AW84: 0 | AX84: 86.25 | AY84: 1 | AZ84: 01 | 0-6 months | BA84: 10 | BB84: Very High | BC84: 1
A85: 0134-XWXCE | B85: Female | C85: 76 | D85: No | E85: 0 | F85: Santa Monica | G85: 90403 | H85: 34.031529 | I85: -118.49116 | J85: 0 | K85: 44 | L85: None | M85: Yes | N85: 7.72 | O85: No | P85: Yes | Q85: DSL | R85: 17.0 | S85: No | T85: No | U85: Yes | V85: Yes | W85: Yes | X85: Yes | Y85: Yes | Z85: Yes | AA85: One Year | AB85: No | AC85: Bank Withdrawal | AD85: 74.85 | AE85: 3268.05 | AF85: 17.91 | AG85: 0 | AH85: 339.68 | AI85: 3589.82 | AJ85: Stayed | AM85: 0 | AN85: 1 | AO85: 0 | AP85: 37-48 months | AQ85: 70+ | AR85: $70-89 | AS85: 6 | AT85: 23559 | AU85: 1 | AV85: 0 | AW85: 1 | AX85: 0 | AY85: 5 | AZ85: 05 | 37-48 months | BA85: 2 | BB85: Medium | BC85: 3
A86: 0135-NMXAP | B86: Female | C86: 57 | D86: No | E86: 0 | F86: Lodi | G86: 95240 | H86: 38.123544 | I86: -121.15908 | J86: 0 | K86: 12 | L86: Offer D | M86: Yes | N86: 14.38 | O86: Yes | P86: Yes | Q86: Fiber Optic | R86: 6.0 | S86: No | T86: Yes | U86: No | V86: No | W86: Yes | X86: No | Y86: No | Z86: Yes | AA86: Month-to-Month | AB86: Yes | AC86: Bank Withdrawal | AD86: 89.75 | AE86: 1052.4 | AF86: 0 | AG86: 0 | AH86: 172.56 | AI86: 1224.96 | AJ86: Churned | AK86: Attitude | AL86: Attitude of support person | AM86: 1 | AN86: 0 | AO86: 0 | AP86: 7-12 months | AQ86: 50-59 | AR86: $70-89 | AS86: 3 | AT86: 45755 | AU86: 1 | AV86: 1 | AW86: 0 | AX86: 89.75 | AY86: 2 | AZ86: 02 | 7-12 months | BA86: 7 | BB86: Very High | BC86: 1
A87: 0136-IFMYD | B87: Male | C87: 71 | D87: Yes | E87: 0 | F87: Los Angeles | G87: 90001 | H87: 33.973616 | I87: -118.24902 | J87: 1 | K87: 69 | L87: None | M87: Yes | N87: 18.41 | O87: Yes | P87: Yes | Q87: Fiber Optic | R87: 17.0 | S87: No | T87: Yes | U87: Yes | V87: Yes | W87: Yes | X87: Yes | Y87: No | Z87: Yes | AA87: Two Year | AB87: Yes | AC87: Bank Withdrawal | AD87: 109.95 | AE87: 7634.25 | AF87: 0 | AG87: 0 | AH87: 1270.29 | AI87: 8904.54 | AJ87: Stayed | AM87: 0 | AN87: 1 | AO87: 0 | AP87: 49-72 months | AQ87: 70+ | AR87: $90+ | AS87: 6 | AT87: 54492 | AU87: 1 | AV87: 0 | AW87: 1 | AX87: 0 | AY87: 6 | AZ87: 06 | 49-72 months | BA87: 3 | BB87: Medium | BC87: 3
A88: 0137-OCGAB | B88: Female | C88: 25 | D88: No | E88: 0 | F88: Fairfield | G88: 94533 | H88: 38.287136 | I88: -122.02711 | J88: 0 | K88: 1 | L88: Offer E | M88: Yes | N88: 1.23 | O88: Yes | P88: Yes | Q88: Fiber Optic | R88: 69.0 | S88: No | T88: Yes | U88: No | V88: No | W88: No | X88: No | Y88: No | Z88: Yes | AA88: Month-to-Month | AB88: Yes | AC88: Mailed Check | AD88: 80.2 | AE88: 80.2 | AF88: 0 | AG88: 0 | AH88: 1.23 | AI88: 81.43 | AJ88: Churned | AK88: Price | AL88: Lack of affordable download/upload speed | AM88: 1 | AN88: 0 | AO88: 0 | AP88: 0-6 months | AQ88: Under 30 | AR88: $70-89 | AS88: 2 | AT88: 77683 | AU88: 1 | AV88: 1 | AW88: 0 | AX88: 80.2 | AY88: 1 | AZ88: 01 | 0-6 months | BA88: 10 | BB88: Very High | BC88: 1
A89: 0137-UDEUO | B89: Female | C89: 24 | D89: No | E89: 0 | F89: Stockton | G89: 95204 | H89: 37.974498 | I89: -121.31957 | J89: 0 | K89: 3 | L89: Offer E | M89: Yes | N89: 25.75 | O89: No | P89: No | Q89: N/A | R89: N/A | S89: N/A | T89: N/A | U89: N/A | V89: N/A | W89: N/A | X89: N/A | Y89: N/A | Z89: N/A | AA89: Month-to-Month | AB89: No | AC89: Credit Card | AD89: 19.85 | AE89: 63.75 | AF89: 0 | AG89: 0 | AH89: 77.25 | AI89: 141 | AJ89: Churned | AK89: Price | AL89: Long distance charges | AM89: 1 | AN89: 0 | AO89: 0 | AP89: 0-6 months | AQ89: Under 30 | AR89: Low (<$30) | AT89: 30476 | AU89: 1 | AV89: 1 | AW89: 0 | AX89: 19.85 | AY89: 1 | AZ89: 01 | 0-6 months | BA89: 8 | BB89: Very High | BC89: 1
A90: 0139-IVFJG | B90: Female | C90: 19 | D90: Yes | E90: 0 | F90: Temecula | G90: 92592 | H90: 33.507255 | I90: -117.02947 | J90: 10 | K90: 2 | L90: None | M90: Yes | N90: 4.65 | O90: No | P90: Yes | Q90: Fiber Optic | R90: 53.0 | S90: Yes | T90: Yes | U90: No | V90: No | W90: Yes | X90: No | Y90: No | Z90: Yes | AA90: Month-to-Month | AB90: No | AC90: Bank Withdrawal | AD90: 90.35 | AE90: 190.5 | AF90: 0 | AG90: 0 | AH90: 9.3 | AI90: 199.8 | AJ90: Joined | AM90: 0 | AN90: 0 | AO90: 0 | AP90: 0-6 months | AQ90: Under 30 | AR90: $90+ | AS90: 4 | AT90: 46171 | AU90: 0 | AX90: 0 | AY90: 1 | AZ90: 01 | 0-6 months | BA90: 9 | BB90: Very High | BC90: 1
A91: 0141-YEAYS | B91: Female | C91: 77 | D91: No | E91: 0 | F91: Fallbrook | G91: 92028 | H91: 33.362575 | I91: -117.29964 | J91: 0 | K91: 27 | L91: None | M91: Yes | N91: 2.97 | O91: Yes | P91: Yes | Q91: Fiber Optic | R91: 4.0 | S91: No | T91: Yes | U91: Yes | V91: No | W91: No | X91: No | Y91: No | Z91: Yes | AA91: Two Year | AB91: Yes | AC91: Bank Withdrawal | AD91: 86.45 | AE91: 2401.05 | AF91: 0 | AG91: 0 | AH91: 80.19 | AI91: 2481.24 | AJ91: Stayed | AM91: 0 | AN91: 1 | AO91: 0 | AP91: 25-36 months | AQ91: 70+ | AR91: $70-89 | AS91: 3 | AT91: 42239 | AU91: 1 | AV91: 0 | AW91: 1 | AX91: 0 | AY91: 4 | AZ91: 04 | 25-36 months | BA91: 4 | BB91: High | BC91: 2
A92: 0142-GVYSN | B92: Male | C92: 57 | D92: No | E92: 0 | F92: Randsburg | G92: 93554 | H92: 35.405722 | I92: -117.77335 | J92: 0 | K92: 26 | L92: Offer C | M92: Yes | N92: 13.34 | O92: No | P92: No | Q92: N/A | R92: N/A | S92: N/A | T92: N/A | U92: N/A | V92: N/A | W92: N/A | X92: N/A | Y92: N/A | Z92: N/A | AA92: Month-to-Month | AB92: Yes | AC92: Bank Withdrawal | AD92: 20.3 | AE92: 511.25 | AF92: 0 | AG92: 0 | AH92: 346.84 | AI92: 858.09 | AJ92: Stayed | AM92: 0 | AN92: 1 | AO92: 0 | AP92: 25-36 months | AQ92: 50-59 | AR92: Low (<$30) | AT92: 117 | AU92: 1 | AV92: 0 | AW92: 1 | AX92: 0 | AY92: 4 | AZ92: 04 | 25-36 months | BA92: 5 | BB92: High | BC92: 2
A93: 0147-ESWWR | B93: Female | C93: 73 | D93: Yes | E93: 0 | F93: Atascadero | G93: 93422 | H93: 35.453912 | I93: -120.69461 | J93: 9 | K93: 39 | L93: None | M93: Yes | N93: 20.15 | O93: Yes | P93: Yes | Q93: Fiber Optic | R93: 21.0 | S93: No | T93: No | U93: No | V93: Yes | W93: Yes | X93: Yes | Y93: Yes | Z93: Yes | AA93: Month-to-Month | AB93: Yes | AC93: Bank Withdrawal | AD93: 101.25 | AE93: 3949.15 | AF93: 0 | AG93: 0 | AH93: 785.85 | AI93: 4735 | AJ93: Stayed | AM93: 0 | AN93: 1 | AO93: 0 | AP93: 37-48 months | AQ93: 70+ | AR93: $90+ | AS93: 5 | AT93: 29539 | AU93: 1 | AV93: 0 | AW93: 1 | AX93: 0 | AY93: 5 | AZ93: 05 | 37-48 months | BA93: 6 | BB93: Very High | BC93: 1
A94: 0148-DCDOS | B94: Male | C94: 41 | D94: No | E94: 0 | F94: Planada | G94: 95365 | H94: 37.329725 | I94: -120.3064 | J94: 0 | K94: 25 | L94: None | M94: Yes | N94: 34.88 | O94: Yes | P94: Yes | Q94: Fiber Optic | R94: 8.0 | S94: No | T94: No | U94: No | V94: No | W94: Yes | X94: Yes | Y94: Yes | Z94: Yes | AA94: Month-to-Month | AB94: Yes | AC94: Bank Withdrawal | AD94: 94.7 | AE94: 2362.1 | AF94: 0 | AG94: 0 | AH94: 872 | AI94: 3234.1 | AJ94: Churned | AK94: Competitor | AL94: Competitor had better devices | AM94: 1 | AN94: 0 | AO94: 0 | AP94: 25-36 months | AQ94: 40-49 | AR94: $90+ | AS94: 4 | AT94: 4150 | AU94: 1 | AV94: 1 | AW94: 0 | AX94: 94.7 | AY94: 4 | AZ94: 04 | 25-36 months | BA94: 7 | BB94: Very High | BC94: 1
A95: 0151-ONTOV | B95: Female | C95: 43 | D95: No | E95: 0 | F95: Moorpark | G95: 93021 | H95: 34.312945 | I95: -118.85817 | J95: 0 | K95: 1 | L95: Offer E | M95: Yes | N95: 39.81 | O95: No | P95: Yes | Q95: Fiber Optic | R95: 23.0 | S95: No | T95: No | U95: No | V95: No | W95: No | X95: No | Y95: No | Z95: Yes | AA95: Month-to-Month | AB95: No | AC95: Mailed Check | AD95: 70.9 | AE95: 70.9 | AF95: 0 | AG95: 0 | AH95: 39.81 | AI95: 110.71 | AJ95: Churned | AK95: Competitor | AL95: Competitor had better devices | AM95: 1 | AN95: 0 | AO95: 0 | AP95: 0-6 months | AQ95: 40-49 | AR95: $70-89 | AS95: 1 | AT95: 32984 | AU95: 1 | AV95: 1 | AW95: 0 | AX95: 70.9 | AY95: 1 | AZ95: 01 | 0-6 months | BA95: 10 | BB95: Very High | BC95: 1
A96: 0156-FVPTA | B96: Male | C96: 48 | D96: Yes | E96: 0 | F96: Solvang | G96: 93463 | H96: 34.624399 | I96: -120.13787 | J96: 1 | K96: 22 | L96: Offer D | M96: Yes | N96: 27.24 | O96: No | P96: Yes | Q96: DSL | R96: 21.0 | S96: Yes | T96: No | U96: No | V96: Yes | W96: No | X96: No | Y96: No | Z96: Yes | AA96: Month-to-Month | AB96: Yes | AC96: Bank Withdrawal | AD96: 54.2 | AE96: 1152.7 | AF96: 0 | AG96: 0 | AH96: 599.28 | AI96: 1751.98 | AJ96: Churned | AK96: Attitude | AL96: Attitude of service provider | AM96: 1 | AN96: 0 | AO96: 0 | AP96: 13-24 months | AQ96: 40-49 | AR96: $50-69 | AS96: 3 | AT96: 7958 | AU96: 1 | AV96: 1 | AW96: 0 | AX96: 54.2 | AY96: 3 | AZ96: 03 | 13-24 months | BA96: 4 | BB96: High | BC96: 2
A97: 0164-APGRB | B97: Female | C97: 56 | D97: No | E97: 0 | F97: Calistoga | G97: 94515 | H97: 38.629618 | I97: -122.59322 | J97: 0 | K97: 72 | L97: Offer A | M97: Yes | N97: 48.37 | O97: Yes | P97: Yes | Q97: Fiber Optic | R97: 5.0 | S97: Yes | T97: Yes | U97: Yes | V97: Yes | W97: Yes | X97: Yes | Y97: Yes | Z97: Yes | AA97: Two Year | AB97: Yes | AC97: Bank Withdrawal | AD97: 114.9 | AE97: 8496.7 | AF97: 0 | AG97: 0 | AH97: 3482.64 | AI97: 11979.34 | AJ97: Stayed | AM97: 0 | AN97: 1 | AO97: 0 | AP97: 49-72 months | AQ97: 50-59 | AR97: $90+ | AS97: 8 | AT97: 7384 | AU97: 1 | AV97: 0 | AW97: 1 | AX97: 0 | AY97: 6 | AZ97: 06 | 49-72 months | BA97: 4 | BB97: High | BC97: 2
A98: 0164-XAIRP | B98: Female | C98: 51 | D98: No | E98: 0 | F98: La Mirada | G98: 90638 | H98: 33.902045 | I98: -118.00896 | J98: 0 | K98: 24 | L98: None | M98: Yes | N98: 10.64 | O98: No | P98: No | Q98: N/A | R98: N/A | S98: N/A | T98: N/A | U98: N/A | V98: N/A | W98: N/A | X98: N/A | Y98: N/A | Z98: N/A | AA98: Two Year | AB98: Yes | AC98: Bank Withdrawal | AD98: 19.55 | AE98: 470.2 | AF98: 0 | AG98: 0 | AH98: 255.36 | AI98: 725.56 | AJ98: Stayed | AM98: 0 | AN98: 1 | AO98: 0 | AP98: 13-24 months | AQ98: 50-59 | AR98: Low (<$30) | AT98: 47568 | AU98: 1 | AV98: 0 | AW98: 1 | AX98: 0 | AY98: 3 | AZ98: 03 | 13-24 months | BA98: 2 | BB98: Medium | BC98: 3
A99: 0168-XZKBB | B99: Female | C99: 34 | D99: Yes | E99: 0 | F99: Boron | G99: 93516 | H99: 34.95703 | I99: -117.73045 | J99: 8 | K99: 19 | L99: None | M99: Yes | N99: 7.84 | O99: Yes | P99: Yes | Q99: Fiber Optic | R99: 16.0 | S99: No | T99: No | U99: No | V99: No | W99: Yes | X99: No | Y99: No | Z99: Yes | AA99: Month-to-Month | AB99: Yes | AC99: Bank Withdrawal | AD99: 86.85 | AE99: 1564.4 | AF99: 0 | AG99: 0 | AH99: 148.96 | AI99: 1713.36 | AJ99: Stayed | AM99: 0 | AN99: 1 | AO99: 0 | AP99: 13-24 months | AQ99: 30-39 | AR99: $70-89 | AS99: 2 | AT99: 2241 | AU99: 1 | AV99: 0 | AW99: 1 | AX99: 0 | AY99: 3 | AZ99: 03 | 13-24 months | BA99: 6 | BB99: Very High | BC99: 1
A100: 0174-QRVVY | B100: Male | C100: 21 | D100: Yes | E100: 2 | F100: San Marcos | G100: 92078 | H100: 33.119028 | I100: -117.16604 | J100: 2 | K100: 71 | L100: None | M100: Yes | N100: 9.2 | O100: Yes | P100: No | Q100: N/A | R100: N/A | S100: N/A | T100: N/A | U100: N/A | V100: N/A | W100: N/A | X100: N/A | Y100: N/A | Z100: N/A | AA100: Two Year | AB100: No | AC100: Credit Card | AD100: 25.35 | AE100: 1847.55 | AF100: 0 | AG100: 0 | AH100: 653.2 | AI100: 2500.75 | AJ100: Stayed | AM100: 0 | AN100: 1 | AO100: 0 | AP100: 49-72 months | AQ100: Under 30 | AR100: Low (<$30) | AT100: 6760 | AU100: 1 | AV100: 0 | AW100: 1 | AX100: 0 | AY100: 6 | AZ100: 06 | 49-72 months | BA100: 0 | BB100: Low | BC100: 4
...
